FPGA-Learning-Repository/module_6_7_FSM/moore/moore_fsm.v
module moore_1011_detector (
    input  wire clk,
    input  wire rst,     // reset asynchronous, active high
    input  wire w,       // input serial bit
    output wire z         // output: 1 saat pola 1011 terdeteksi
);

    // Encoding state pakai Gray code (Q2 Q1 Q0)
    localparam S0 = 3'b000; // belum ada progres
    localparam S1 = 3'b001; // sudah "1"
    localparam S2 = 3'b011; // sudah "10"
    localparam S3 = 3'b010; // sudah "101"
    localparam S4 = 3'b110; // sudah "1011" -> output 1

    reg [2:0] state, next_state;

    // Next-state logic (kombinasional)
    always @(*) begin
        case (state)
            S0: next_state = w ? S1 : S0;
            S1: next_state = w ? S1 : S2;
            S2: next_state = w ? S3 : S2;
            S3: next_state = w ? S4 : S3;
            S4: next_state = w ? S1 : S2;
            default: next_state = S0; // handle unused/don't-care states
        endcase
    end

    // State register (3 D flip-flop)
    always @(posedge clk or posedge rst) begin
        if (rst)
            state <= S0;
        else
            state <= next_state;
    end

    // Output logic (Moore: hanya bergantung state)
    assign z = (state == S4);

endmodule

FPGA-Learning-Repository/module_6_7_FSM/moore/moore_fsm_tb.v
`timescale 1ns/1ps

module tb_moore_1011_detector;

    reg clk;
    reg rst;
    reg w;
    wire z;

    // Instansiasi DUT (Device Under Test)
    moore_1011_detector uut (
        .clk(clk),
        .rst(rst),
        .w(w),
        .z(z)
    );

    // Generate clock, periode 10ns
    always #5 clk = ~clk;

    initial begin
        // Inisialisasi
        clk = 0;
        rst = 1;
        w   = 0;
        #10;
        rst = 0;

        // Test urutan: 1 0 1 1 0 1 1 (ada overlap 1011 di posisi 4 dan cek overlap lagi)
        // Setiap bit dikirim 1 clock cycle
        send_bit(1'b1);
        send_bit(1'b0);
        send_bit(1'b1);
        send_bit(1'b1);   // -> di sini seharusnya z=1 (pola 1011 pertama terdeteksi)
        send_bit(1'b0);
        send_bit(1'b1);
        send_bit(1'b1);   // -> cek overlap kedua

        #20;
        $finish;
    end

    task send_bit(input b);
        begin
            w = b;
            @(posedge clk);
            #1; // beri jeda kecil supaya z sempat update sebelum dicetak
            $display("Time=%0t | w=%b | state=%b | z=%b", $time, w, uut.state, z);
        end
    endtask

    // Dump waveform untuk dilihat di GTKWave/simulator
    initial begin
        $dumpfile("moore_1011.vcd");
        $dumpvars(0, tb_moore_1011_detector);
    end

endmodule

module_6_7_FSM/moore/moore_1011.vcd
$date
	Thu Sep 17 10:03:51 2026
$end
$version
	Icarus Verilog
$end
$timescale
	1ps
$end
$scope module tb_moore_1011_detector $end
$var wire 1 ! z $end
$var reg 1 " clk $end
$var reg 1 # rst $end
$var reg 1 $ w $end
$scope module uut $end
$var wire 1 " clk $end
$var wire 1 # rst $end
$var wire 1 $ w $end
$var wire 1 ! z $end
$var parameter 3 % S0 $end
$var parameter 3 & S1 $end
$var parameter 3 ' S2 $end
$var parameter 3 ( S3 $end
$var parameter 3 ) S4 $end
$var reg 3 * next_state [2:0] $end
$var reg 3 + state [2:0] $end
$upscope $end
$scope task send_bit $end
$var reg 1 , b $end
$upscope $end
$upscope $end
$enddefinitions $end
$comment Show the parameter values. $end
$dumpall
b110 )
b10 (
b11 '
b1 &
b0 %
$end
#0
$dumpvars
x,
b0 +
b0 *
0$
1#
0"
0!
$end
#5000
1"
#10000
b1 *
0"
1$
1,
0#
#15000
b1 +
1"
#16000
b11 *
0$
0,
#20000
0"
#25000
b11 +
1"
#26000
b10 *
1$
1,
#30000
0"
#35000
b110 *
b10 +
1"
#40000
0"
#45000
b1 *
1!
b110 +
1"
#46000
b11 *
0$
0,
#50000
0"
#55000
0!
b11 +
1"
#56000
b10 *
1$
1,
#60000
0"
#65000
b110 *
b10 +
1"
#70000
0"
#75000
b1 *
1!
b110 +
1"
#80000
0"
#85000
0!
b1 +
1"
