FPGA-Learning-Repository/module_3_sequential_circuit/jkff_ms.v
//==========================================================================
//  jkff_ms.v  --  J-K master-slave flip-flop (Module 1, section 9)
//
//  Characteristic equation :  Q(t+1) = J Q(t)' + K' Q(t)
//  Reference figures       :  Figure 1.19   (NAND circuit)
//                             Figure 1.20   (block diagram and circuit)
//                             Figure 1.20.d (frequency divider)
//                             Figure 1.20.e (IC 7476 pin assignment)
//                             Figure 1.21   (1s catching / 0s catching)
//  Reference tables        :  Table 1.12, 1.13, 1.13.a
//
//  Three feedback paths are present, exactly as described in the module:
//    * the flip-flop feedback of the master section,
//    * the flip-flop feedback of the slave section,
//    * the toggle feedback, in which the slave outputs Q and Q' are
//      returned to the 3-input NAND gates at the input of the master.
//  It is the toggle feedback that turns J = K = 1 into a toggle instead of
//  the forbidden state of the S-R flip-flop.
//==========================================================================
`timescale 1ns / 1ps


//--------------------------------------------------------------------------
//  Gate level (Figure 1.19)
//--------------------------------------------------------------------------
module jkff_ms_gate (
    input  wire J,
    input  wire K,
    input  wire C,
    output wire Q,
    output wire QN
);

    wire c_n;
    wire s_n, r_n;          // master input gates (active low)
    wire qm, qmn;           // master outputs
    wire sm_n, rm_n;        // slave input gates (active low)

    not #1 g0 (c_n, C);

    // Master input gates: 3 inputs each, including the toggle feedback
    nand #1 g1 (s_n, J, C, QN);
    nand #1 g2 (r_n, K, C, Q );

    // Master latch
    nand #1 g3 (qm , s_n, qmn);
    nand #1 g4 (qmn, r_n, qm );

    // Slave input gates, enabled while C = 0
    nand #1 g5 (sm_n, qm , c_n);
    nand #1 g6 (rm_n, qmn, c_n);

    // Slave latch
    nand #1 g7 (Q , sm_n, QN);
    nand #1 g8 (QN, rm_n, Q );

endmodule


//--------------------------------------------------------------------------
//  Behavioural model (Table 1.13)
//  The output changes on the falling edge of C.
//--------------------------------------------------------------------------
module jkff_ms (
    input  wire J,
    input  wire K,
    input  wire C,
    output reg  Q,
    output wire QN
);

    assign QN = ~Q;

    always @(negedge C) begin
        Q <= (J & ~Q) | (~K & Q);       // Q(t+1) = J Q' + K' Q
    end

endmodule


//--------------------------------------------------------------------------
//  Behavioural model of one half of a 7476 / 74LS76, that is, a J-K
//  master-slave flip-flop with asynchronous preset and clear, both ACTIVE
//  LOW (Figure 1.20.e, Table 1.13.a).
//--------------------------------------------------------------------------
module jkff_ms_7476 (
    input  wire J,
    input  wire K,
    input  wire CLK,
    input  wire PRE_N,          // asynchronous preset, active LOW
    input  wire CLR_N,          // asynchronous clear,  active LOW
    output reg  Q,
    output wire QN
);

    // In the forbidden state both outputs are high, so QN is not ~Q there.
    assign QN = (~PRE_N & ~CLR_N) ? 1'b1 : ~Q;

    always @(negedge CLK or negedge PRE_N or negedge CLR_N) begin
        if (!PRE_N && !CLR_N) Q <= 1'b1;                // forbidden
        else if (!PRE_N)      Q <= 1'b1;                // preset
        else if (!CLR_N)      Q <= 1'b0;                // clear
        else                  Q <= (J & ~Q) | (~K & Q); // synchronous
    end

endmodule

module_3_sequential_circuit/tb_jkff_ms.v
`timescale 1ns / 1ps

module tb_jkff_ms();

    reg J_7476, K_7476, CLK_7476, PRE_N, CLR_N;
    wire Q_7476, QN_7476;

    jkff_ms_7476 uut_7476 (
        .J(J_7476), .K(K_7476), .CLK(CLK_7476),
        .PRE_N(PRE_N), .CLR_N(CLR_N),
        .Q(Q_7476), .QN(QN_7476)
    );

    reg J_gate, K_gate, C_gate;
    wire Q_gate, QN_gate;

    jkff_ms_gate uut_gate (
        .J(J_gate), .K(K_gate), .C(C_gate),
        .Q(Q_gate), .QN(QN_gate)
    );

    initial begin
        CLK_7476 = 1; C_gate = 1;
        forever begin
            #5 CLK_7476 = ~CLK_7476;
               C_gate   = ~C_gate;
        end
    end

    initial begin
        $dumpfile("tb_jkff_ms.vcd");
        $dumpvars(0, tb_jkff_ms);

        $display("===== ASYNC PRESET, CLEAR & RACE CONDITION =====");
        $display("PRE_N CLR_N CLK J K | Q QN | Mode");
        J_7476 = 0; K_7476 = 0;
        
        PRE_N = 0; CLR_N = 1; #10;
        $display("  %b     %b    X  X X | %b  %b | Preset (asynchronous)", PRE_N, CLR_N, Q_7476, QN_7476);

        PRE_N = 1; CLR_N = 0; #10;
        $display("  %b     %b    X  X X | %b  %b | Clear (asynchronous)", PRE_N, CLR_N, Q_7476, QN_7476);
        
        PRE_N = 0; CLR_N = 0; #10;
        $display("  %b     %b    X  X X | %b  %b | Forbidden (Race Condition)", PRE_N, CLR_N, Q_7476, QN_7476);

        PRE_N = 1; CLR_N = 0; #5;
        PRE_N = 1; CLR_N = 1; #5;

        $display("\n===== TOGGLE MODE (DIVIDE BY TWO) =====");
        $display("PRE_N CLR_N CLK J K | Q QN | Mode");
        J_7476 = 1; K_7476 = 1; 
        
        @(negedge CLK_7476); #1;
        $display("  %b     %b    F  %b %b | %b  %b | Toggle", PRE_N, CLR_N, J_7476, K_7476, Q_7476, QN_7476);
        @(negedge CLK_7476); #1;
        $display("  %b     %b    F  %b %b | %b  %b | Toggle", PRE_N, CLR_N, J_7476, K_7476, Q_7476, QN_7476);
        @(negedge CLK_7476); #1;
        $display("  %b     %b    F  %b %b | %b  %b | Toggle", PRE_N, CLR_N, J_7476, K_7476, Q_7476, QN_7476);

        $display("\n===== 1s CATCHING (GATE LEVEL) =====");
        $display("CLK J K | Q | Event Description");
        
        J_gate = 0; K_gate = 1; 
        @(negedge C_gate); #2; 
        $display(" %b  %b %b | %b | Initial state (Reset)", C_gate, J_gate, K_gate, Q_gate);
        
        J_gate = 0; K_gate = 0; 
        
        wait(C_gate == 1); 
        #1;
        J_gate = 1;      
        $display(" %b  %b %b | %b | Narrow pulse applied to J while CLK is HIGH", C_gate, J_gate, K_gate, Q_gate);
        #2;
        J_gate = 0;        
        $display(" %b  %b %b | %b | Narrow pulse removed from J before CLK falls", C_gate, J_gate, K_gate, Q_gate);
        
        wait(C_gate == 0); 
        #2;               
        $display(" %b  %b %b | %b | After falling edge (1s caught by master!)", C_gate, J_gate, K_gate, Q_gate);

        $display("\nSimulation complete.");
        $finish;
    end

endmodule

FPGA-Learning-Repository/module_3_sequential_circuit/tb_jkff_ms.vcd
$date
	Thu Sep 10 21:34:53 2026
$end
$version
	Icarus Verilog
$end
$timescale
	1ps
$end
$scope module tb_jkff_ms $end
$var wire 1 ! Q_gate $end
$var wire 1 " Q_7476 $end
$var wire 1 # QN_gate $end
$var wire 1 $ QN_7476 $end
$var reg 1 % CLK_7476 $end
$var reg 1 & CLR_N $end
$var reg 1 ' C_gate $end
$var reg 1 ( J_7476 $end
$var reg 1 ) J_gate $end
$var reg 1 * K_7476 $end
$var reg 1 + K_gate $end
$var reg 1 , PRE_N $end
$scope module uut_7476 $end
$var wire 1 % CLK $end
$var wire 1 & CLR_N $end
$var wire 1 ( J $end
$var wire 1 * K $end
$var wire 1 , PRE_N $end
$var wire 1 $ QN $end
$var reg 1 " Q $end
$upscope $end
$scope module uut_gate $end
$var wire 1 ' C $end
$var wire 1 ) J $end
$var wire 1 + K $end
$var wire 1 ! Q $end
$var wire 1 # QN $end
$var wire 1 - c_n $end
$var wire 1 . qm $end
$var wire 1 / qmn $end
$var wire 1 0 r_n $end
$var wire 1 1 rm_n $end
$var wire 1 2 s_n $end
$var wire 1 3 sm_n $end
$upscope $end
$upscope $end
$enddefinitions $end
$comment Show the parameter values. $end
$dumpall
$end
#0
$dumpvars
x3
x2
x1
x0
x/
x.
x-
0,
x+
0*
x)
0(
1'
1&
1%
0$
x#
1"
x!
$end
#1000
0-
#2000
13
11
#5000
0'
0%
#6000
1-
12
10
#7000
x3
x1
#10000
1$
0"
1'
1%
0&
1,
#11000
0-
x2
x0
#12000
13
11
#15000
0'
0%
#16000
1-
12
10
#17000
x3
x1
#20000
1"
1'
1%
0,
#21000
0-
x2
x0
#22000
13
11
#25000
0'
0%
#26000
1-
12
10
#27000
x3
x1
#30000
0$
1'
1%
1,
#31000
0-
x2
x0
#32000
13
11
#35000
0'
0%
1&
#36000
1-
12
10
#37000
x3
x1
#40000
1'
1%
1*
1(
#41000
0-
x2
x0
#42000
13
11
#45000
1$
0"
0'
0%
#46000
1-
12
10
#47000
x3
x1
#50000
1'
1%
#51000
0-
x2
x0
#52000
13
11
#55000
0$
1"
0'
0%
#56000
1-
12
10
#57000
x3
x1
#60000
1'
1%
#61000
0-
x2
x0
#62000
13
11
#65000
1$
0"
0'
0%
#66000
1-
12
10
1+
0)
#67000
x3
x1
#70000
1'
1%
#71000
0-
x0
#72000
13
11
#75000
0$
1"
0'
0%
#76000
1-
10
#77000
x3
x1
0+
#80000
1'
1%
#81000
0-
1)
#82000
13
11
x2
#83000
0)
#84000
12
#85000
1$
0"
0'
0%
#86000
1-
#87000
x3
x1
