FPGA-Learning-Repository/module_5_counters/dff_t.v
`timescale 1ns / 1ps
//======================================================================
//  dff_t.v  --  D flip-flop with a modelled clock-to-Q delay, and a
//               behavioural setup/hold checker
//----------------------------------------------------------------------
//  Module 4 : Sequential Circuit Practice I
//
//  dff_t              : rising-edge D flip-flop, asynchronous active-low
//                       reset, clock-to-Q delay TPD (ns). The delay makes
//                       timing VISIBLE and MEASURABLE in the waveform.
//  setup_hold_checker : watches a data input relative to the clock edge
//                       and reports every setup or hold violation. It is
//                       a simulation-only instrument (never synthesised).
//======================================================================

module dff_t #(
    parameter TPD = 1.0                 // clock-to-Q delay in ns
)(
    input  wire clk, rstn, d,
    output reg  q
);
    always @(posedge clk or negedge rstn)
        if (!rstn) q <= #TPD 1'b0;
        else       q <= #TPD d;          // intra-assignment delay
endmodule


module setup_hold_checker #(
    parameter real T_SETUP = 2.0,       // ns before the edge: d must be stable
    parameter real T_HOLD  = 1.0        // ns after the edge:  d must stay stable
)(
    input wire clk, d
);
    realtime t_d   = -1.0e9;            // time of the last change of d
    realtime t_clk = -1.0e9;            // time of the last rising clock edge
    integer  violations = 0;

    always @(d) begin
        t_d = $realtime;
        if (t_clk >= 0 && (t_d - t_clk) < T_HOLD) begin
            violations = violations + 1;
            $display("   !! HOLD  violation at %0t : d changed %0.1f ns after the edge (need %0.1f)",
                     $realtime, t_d - t_clk, T_HOLD);
        end
    end

    always @(posedge clk) begin
        t_clk = $realtime;
        if (t_d >= 0 && (t_clk - t_d) < T_SETUP) begin
            violations = violations + 1;
            $display("   !! SETUP violation at %0t : d changed %0.1f ns before the edge (need %0.1f)",
                     $realtime, t_clk - t_d, T_SETUP);
        end
    end
endmodule

FPGA-Learning-Repository/module_4_shift_registers/shift_registers.v
`timescale 1ns / 1ps
//======================================================================
//  shift_registers.v  --  PIPO, SIPO, SISO, PISO, bidirectional, universal
//----------------------------------------------------------------------
//  Module 4 : Sequential Circuit Practice I
//
//  Bit convention : q[3] is the leftmost stage (QA), q[0] the rightmost
//                   (QD). "Shift right" moves data QA -> QB -> QC -> QD.
//  Serial data     : entered least-significant bit first.
//  The structural registers are built from dff_t (clock-to-Q = TPD);
//  universal4 is the behavioural (RTL) form used for synthesis.
//======================================================================

//---------------------------------------------------------- PIPO
module pipo4 (
    input  wire       clk, rstn,
    input  wire       load,             // capture din on the next edge
    input  wire       oe,               // output enable
    input  wire [3:0] din,
    output wire [3:0] q,
    output wire [3:0] dout
);
    wire [3:0] d = load ? din : q;      // hold when load = 0
    dff_t FA (.clk(clk), .rstn(rstn), .d(d[3]), .q(q[3]));
    dff_t FB (.clk(clk), .rstn(rstn), .d(d[2]), .q(q[2]));
    dff_t FC (.clk(clk), .rstn(rstn), .d(d[1]), .q(q[1]));
    dff_t FD (.clk(clk), .rstn(rstn), .d(d[0]), .q(q[0]));
    assign dout = q & {4{oe}};          // four AND gates
endmodule

//---------------------------------------------------------- SIPO
module sipo4 (
    input  wire       clk, rstn,
    input  wire       si,               // serial input
    output wire [3:0] q,
    output wire       so                // serial output = q[0]
);
    dff_t FA (.clk(clk), .rstn(rstn), .d(si),   .q(q[3]));
    dff_t FB (.clk(clk), .rstn(rstn), .d(q[3]), .q(q[2]));
    dff_t FC (.clk(clk), .rstn(rstn), .d(q[2]), .q(q[1]));
    dff_t FD (.clk(clk), .rstn(rstn), .d(q[1]), .q(q[0]));
    assign so = q[0];
endmodule

//---------------------------------------------------------- SISO
module siso4 (
    input  wire clk, rstn, si,
    output wire so
);
    wire [3:0] q;
    sipo4 U (.clk(clk), .rstn(rstn), .si(si), .q(q), .so(so));   // same chain, serial out only
endmodule

//---------------------------------------------------------- PISO
module piso4 (
    input  wire       clk, rstn,
    input  wire       load,             // 1: parallel load, 0: shift out
    input  wire [3:0] din,
    output wire [3:0] q,
    output wire       so
);
    // a 2:1 multiplexer in front of every flip-flop selects load or shift
    wire [3:0] d;
    assign d[3] = load ? din[3] : 1'b0;   // shift in zeros
    assign d[2] = load ? din[2] : q[3];
    assign d[1] = load ? din[1] : q[2];
    assign d[0] = load ? din[0] : q[1];
    dff_t FA (.clk(clk), .rstn(rstn), .d(d[3]), .q(q[3]));
    dff_t FB (.clk(clk), .rstn(rstn), .d(d[2]), .q(q[2]));
    dff_t FC (.clk(clk), .rstn(rstn), .d(d[1]), .q(q[1]));
    dff_t FD (.clk(clk), .rstn(rstn), .d(d[0]), .q(q[0]));
    assign so = q[0];
endmodule

//---------------------------------------------------------- bidirectional
module bidir4 (
    input  wire       clk, rstn,
    input  wire       dir,              // 1: shift right, 0: shift left
    input  wire       sir,              // serial input for shift right (enters at q[3])
    input  wire       sil,              // serial input for shift left  (enters at q[0])
    output wire [3:0] q
);
    wire [3:0] d;
    assign d[3] = dir ? sir  : q[2];
    assign d[2] = dir ? q[3] : q[1];
    assign d[1] = dir ? q[2] : q[0];
    assign d[0] = dir ? q[1] : sil;
    dff_t FA (.clk(clk), .rstn(rstn), .d(d[3]), .q(q[3]));
    dff_t FB (.clk(clk), .rstn(rstn), .d(d[2]), .q(q[2]));
    dff_t FC (.clk(clk), .rstn(rstn), .d(d[1]), .q(q[1]));
    dff_t FD (.clk(clk), .rstn(rstn), .d(d[0]), .q(q[0]));
endmodule

//---------------------------------------------------------- universal (RTL)
//  mode 00 hold | 01 shift right (sir enters at MSB) | 10 shift left | 11 load
module universal4 (
    input  wire       clk, rstn,
    input  wire [1:0] mode,
    input  wire       sir, sil,
    input  wire [3:0] din,
    output reg  [3:0] q
);
    always @(posedge clk or negedge rstn)
        if (!rstn) q <= 4'b0000;
        else case (mode)
            2'b00: q <= q;
            2'b01: q <= {sir, q[3:1]};
            2'b10: q <= {q[2:0], sil};
            2'b11: q <= din;
        endcase
endmodule

module_4_shift_registers/timing_tb.v
`timescale 1ns / 1ps
//======================================================================
//  timing_tb.v  --  Timing verification of the shift-register elements
//----------------------------------------------------------------------
//  Part A : measure the clock-to-Q delay of dff_t (TPD = 1.0 and 2.5 ns)
//  Part B : measure the latency of the 4-stage SISO register (4 clocks)
//  Part C : setup/hold checker -- a clean stimulus reports 0 violations,
//           a deliberately bad stimulus reports one setup and one hold
//  Part D : estimate the maximum clock frequency from measured t_cq and
//           given t_logic / t_setup  (T >= t_cq + t_logic + t_setup)
//======================================================================
module timing_tb;
    reg clk = 0, rstn = 1, d = 0, si = 0;
    always #5 clk = ~clk;                       // 100 MHz, period 10 ns
    wire q1, q2, so;
    integer err = 0, i, edges;
    realtime t_edge, t_q1, t_q2;

    dff_t #(.TPD(1.0)) F1 (.clk(clk), .rstn(rstn), .d(d), .q(q1));
    dff_t #(.TPD(2.5)) F2 (.clk(clk), .rstn(rstn), .d(d), .q(q2));
    siso4              S  (.clk(clk), .rstn(rstn), .si(si), .so(so));

    // checker on the d input of F1 : T_SETUP = 2 ns, T_HOLD = 1 ns
    setup_hold_checker #(.T_SETUP(2.0), .T_HOLD(1.0)) CHK (.clk(clk), .d(d));

    always @(posedge clk) t_edge = $realtime;
    always @(q1) t_q1 = $realtime;
    always @(q2) t_q2 = $realtime;

    initial begin
        $dumpfile("timing_tb.vcd"); $dumpvars(0, timing_tb);
        $timeformat(-9, 1, " ns", 8);
        rstn = 0; #2; rstn = 1;

        // ---------------- Part A ----------------
        $display("");
        $display("  ===== PART A : CLOCK-TO-Q DELAY =====");
        @(negedge clk); d = 1;                   // change d mid-cycle (safe)
        @(posedge clk); #4;                      // wait for both outputs
        $display("   edge at %t : q1 changed at %t  ->  t_cq = %0.1f ns  (TPD = 1.0)", t_edge, t_q1, t_q1 - t_edge);
        $display("   edge at %t : q2 changed at %t  ->  t_cq = %0.1f ns  (TPD = 2.5)", t_edge, t_q2, t_q2 - t_edge);
        if ((t_q1 - t_edge) != 1.0 || (t_q2 - t_edge) != 2.5) begin err = err + 1; $display("   !! t_cq wrong"); end

        // ---------------- Part B ----------------
        $display("");
        $display("  ===== PART B : SISO LATENCY =====");
        @(negedge clk); si = 1; @(negedge clk); si = 0;     // one-clock-wide pulse
        edges = 1;                                          // the pulse was captured on 1 edge
        while (so !== 1'b1 && edges < 20) begin @(posedge clk); #3; edges = edges + 1; end
        $display("   a 1-bit pulse entered on clock 1 appeared at the serial output on clock %0d", edges);
        $display("   -> latency of the 4-stage register = %0d clock periods", edges);
        if (edges !== 4) begin err = err + 1; $display("   !! latency should be 4"); end

        // ---------------- Part C ----------------
        $display("");
        $display("  ===== PART C : SETUP / HOLD CHECK  (T_SETUP = 2 ns, T_HOLD = 1 ns) =====");
        $display("   clean stimulus: d changes 5 ns before every edge");
        for (i = 0; i < 4; i = i + 1) begin @(negedge clk); d = ~d; end
        @(posedge clk); #1;
        $display("   violations so far = %0d", CHK.violations);
        if (CHK.violations !== 0) begin err = err + 1; $display("   !! clean stimulus must not violate"); end

        $display("   bad stimulus (a): d changes 1 ns BEFORE the edge");
        @(posedge clk); #9; d = ~d;                          // 1 ns before next rising edge
        @(posedge clk); #0.1;
        $display("   bad stimulus (b): d changes 0.5 ns AFTER the edge");
        #0.4; d = ~d;                                        // 0.5 ns after the edge
        #2;
        $display("   violations now = %0d  (expected 2: one setup, one hold)", CHK.violations);
        if (CHK.violations !== 2) begin err = err + 1; $display("   !! checker should report exactly 2"); end

        // ---------------- Part D ----------------
        $display("");
        $display("  ===== PART D : MAXIMUM CLOCK FREQUENCY ESTIMATE =====");
        $display("   t_cq = 1.0 ns (measured), t_logic = 3.2 ns (given), t_setup = 2.0 ns (checker)");
        $display("   T_min = 1.0 + 3.2 + 2.0 = 6.2 ns  ->  f_max = %0.1f MHz", 1000.0/6.2);
        $display("   at 100 MHz (T = 10 ns) the slack is 10 - 6.2 = +3.8 ns  (constraint met)");

        $display("");
        if (err == 0) $display("  >> PASS: timing measurements and checks behaved as expected.");
        else          $display("  >> FAIL: %0d problem(s).", err);
        $display("");
        $finish;
    end
endmodule

FPGA-Learning-Repository/module_4_shift_registers/timing_tb.vcd
$date
	Fri Sep 11 15:13:56 2026
$end
$version
	Icarus Verilog
$end
$timescale
	1ps
$end
$scope module timing_tb $end
$var wire 1 ! so $end
$var wire 1 " q2 $end
$var wire 1 # q1 $end
$var reg 1 $ clk $end
$var reg 1 % d $end
$var reg 1 & rstn $end
$var reg 1 ' si $end
$var integer 32 ( edges [31:0] $end
$var integer 32 ) err [31:0] $end
$var integer 32 * i [31:0] $end
$var real 1 + t_edge $end
$var real 1 , t_q1 $end
$var real 1 - t_q2 $end
$scope module CHK $end
$var wire 1 $ clk $end
$var wire 1 % d $end
$var real 1 . T_HOLD $end
$var real 1 / T_SETUP $end
$var real 1 0 t_clk $end
$var real 1 1 t_d $end
$var integer 32 2 violations [31:0] $end
$upscope $end
$scope module F1 $end
$var wire 1 $ clk $end
$var wire 1 % d $end
$var wire 1 & rstn $end
$var real 1 3 TPD $end
$var reg 1 # q $end
$upscope $end
$scope module F2 $end
$var wire 1 $ clk $end
$var wire 1 % d $end
$var wire 1 & rstn $end
$var real 1 4 TPD $end
$var reg 1 " q $end
$upscope $end
$scope module S $end
$var wire 1 $ clk $end
$var wire 1 & rstn $end
$var wire 1 ' si $end
$var wire 1 ! so $end
$var wire 4 5 q [3:0] $end
$scope module U $end
$var wire 1 $ clk $end
$var wire 1 & rstn $end
$var wire 1 ' si $end
$var wire 1 ! so $end
$var wire 4 6 q [3:0] $end
$scope module FA $end
$var wire 1 $ clk $end
$var wire 1 ' d $end
$var wire 1 & rstn $end
$var real 1 7 TPD $end
$var reg 1 8 q $end
$upscope $end
$scope module FB $end
$var wire 1 $ clk $end
$var wire 1 9 d $end
$var wire 1 & rstn $end
$var real 1 : TPD $end
$var reg 1 ; q $end
$upscope $end
$scope module FC $end
$var wire 1 $ clk $end
$var wire 1 < d $end
$var wire 1 & rstn $end
$var real 1 = TPD $end
$var reg 1 > q $end
$upscope $end
$scope module FD $end
$var wire 1 $ clk $end
$var wire 1 ? d $end
$var wire 1 & rstn $end
$var real 1 @ TPD $end
$var reg 1 A q $end
$upscope $end
$upscope $end
$upscope $end
$upscope $end
$enddefinitions $end
$comment Show the parameter values. $end
$dumpall
r1 @
r1 =
r1 :
r1 7
r2.5 4
r1 3
r2 /
r1 .
$end
#0
$dumpvars
xA
x?
x>
x<
x;
x9
x8
bx 6
bx 5
b0 2
r0 1
r-1000000000 0
r0 -
r0 ,
r0 +
bx *
b0 )
bx (
0'
0&
0%
0$
x#
x"
x!
$end
#1000
r1 ,
09
0<
0?
0!
0#
08
0;
0>
b0 5
b0 6
0A
#2000
1&
#2500
r2.5 -
0"
#5000
r5 0
r5 +
1$
#10000
r10 1
1%
0$
#15000
r15 +
r15 0
1$
#16000
r16 ,
1#
#17500
r17.5 -
1"
#20000
1'
0$
#25000
r25 0
r25 +
1$
#26000
19
b1000 5
b1000 6
18
#30000
b1 (
0'
0$
#35000
r35 +
r35 0
1$
#36000
09
1<
08
b100 5
b100 6
1;
#38000
b10 (
#40000
0$
#45000
r45 0
r45 +
1$
#46000
1?
0<
1>
b10 5
b10 6
0;
#48000
b11 (
#50000
0$
#55000
r55 +
r55 0
1$
#56000
0?
1!
0>
b1 5
b1 6
1A
#58000
b0 *
b100 (
#60000
r60 1
b1 *
0%
0$
#65000
r65 0
r65 +
1$
#66000
0!
r66 ,
b0 5
b0 6
0A
0#
#67500
r67.5 -
0"
#70000
r70 1
b10 *
1%
0$
#75000
r75 +
r75 0
1$
#76000
r76 ,
1#
#77500
r77.5 -
1"
#80000
r80 1
b11 *
0%
0$
#85000
r85 0
r85 +
1$
#86000
r86 ,
0#
#87500
r87.5 -
0"
#90000
r90 1
b100 *
1%
0$
#95000
r95 +
r95 0
1$
#96000
r96 ,
1#
#97500
r97.5 -
1"
#100000
0$
#105000
r105 0
r105 +
1$
#110000
0$
#114000
r114 1
0%
#115000
r115 +
b1 2
r115 0
1$
#115500
b10 2
r115.5 1
1%
#116000
r116 ,
0#
#117500
0"
