module_3_sequential_circuit/jkff_edge.v
//==========================================================================
//  jkff_edge.v  --  Edge-triggered J-K flip-flop (Module 1, section 10)
//
//  Characteristic equation :  Q(t+1) = J Q(t)' + K' Q(t)
//  Reference figures       :  Figure 1.22   (block diagram and circuit)
//                             Figure 1.23   (timing diagram)
//                             Figure 1.18.e (negative-edge version)
//  Reference tables        :  Table 1.14, 1.10.a
//
//  As stated in the module, this flip-flop uses an edge-triggered D
//  flip-flop internally.  The gate network in front of it computes
//      D = J Q' + K' Q
//  so that the D flip-flop stores the required next state.  Because the
//  D flip-flop samples only at the clock edge, this circuit does not
//  suffer from 1s catching.
//==========================================================================
`timescale 1ns / 1ps


//--------------------------------------------------------------------------
//  Gate level -- input logic plus an edge-triggered D flip-flop
//  (Figure 1.22 b)
//--------------------------------------------------------------------------
module jkff_edge_gate (
    input  wire J,
    input  wire K,
    input  wire CLK,
    output wire Q,
    output wire QN
);

    wire k_n;               // K'
    wire a1, a2;            // J Q'   and   K' Q
    wire d;                 // D = J Q' + K' Q

    not #1 g0 (k_n, K);
    and #1 g1 (a1, J  , QN);
    and #1 g2 (a2, k_n, Q );
    or #1  g3 (d , a1 , a2);

    d_ff_gate u_dff (.D(d), .CLK(CLK), .Q(Q), .QN(QN));

endmodule


//--------------------------------------------------------------------------
//  Gate level -- negative-edge-triggered version (Figure 1.18.e)
//--------------------------------------------------------------------------
module jkff_negedge_gate (
    input  wire J,
    input  wire K,
    input  wire CLK,
    output wire Q,
    output wire QN
);

    wire k_n, a1, a2, d;

    not #1 g0 (k_n, K);
    and #1 g1 (a1, J  , QN);
    and #1 g2 (a2, k_n, Q );
    or #1  g3 (d , a1 , a2);

    d_ff_neg_gate u_dff (.D(d), .CLK(CLK), .Q(Q), .QN(QN));

endmodule


//--------------------------------------------------------------------------
//  Behavioural model, positive edge (Table 1.14)
//--------------------------------------------------------------------------
module jkff_edge (
    input  wire J,
    input  wire K,
    input  wire CLK,
    output reg  Q,
    output wire QN
);

    assign QN = ~Q;

    always @(posedge CLK) begin
        Q <= (J & ~Q) | (~K & Q);       // Q(t+1) = J Q' + K' Q
    end

endmodule

module_3_sequential_circuit/tb_jkff_edge.v
`timescale 1ns / 1ps

module tb_jkff_edge();

    // Testbench signals
    reg J;
    reg K;
    reg CLK;
    
    wire Q;
    wire QN;

    jkff_edge uut (
        .J(J),
        .K(K),
        .CLK(CLK),
        .Q(Q),
        .QN(QN)
    );

    initial begin
        CLK = 0;
        forever #5 CLK = ~CLK;
    end

    initial begin
        $dumpfile("tb_jkff_edge.vcd");
        $dumpvars(0, tb_jkff_edge);

        J = 0; K = 0;
        
        $display("===== JK CHARACTERISTIC TABLE =====");
        $display("J K | Q(t+1)");
        
        #12;
        J = 1; K = 0; 
        @(posedge CLK); #1; 
        $display("%b %b |   %b   (set)", J, K, Q);
        
        J = 0; K = 0; 
        @(posedge CLK); #1;
        $display("%b %b |   %b   (hold)", J, K, Q);
        
        J = 0; K = 1; 
        @(posedge CLK); #1;
        $display("%b %b |   %b   (reset)", J, K, Q);
        
        J = 1; K = 1; 
        @(posedge CLK); #1;
        $display("%b %b |   %b   (toggle)", J, K, Q);
        
        J = 1; K = 1; 
        @(posedge CLK); #1;
        $display("%b %b |   %b   (toggle)", J, K, Q);


        $display("\n===== VERIFYING NO 1s CATCHING =====");
        
        J = 0; K = 1;
        @(posedge CLK); #1;
        $display("Initial state Q = %b", Q);
        
        J = 0; K = 0;
        
        wait(CLK == 1);   
        #1; 
        J = 1;             
        $display("-> Narrow pulse applied to J while CLK is HIGH");
        #2;
        J = 0;             
        $display("-> Narrow pulse removed from J while CLK is HIGH");
        
        @(posedge CLK); #1; 
        $display("After next clock edge, Q = %b (Expected: 0, pulse was ignored)", Q);

        $display("\nSimulation complete.");
        $finish;
    end

endmodule

module_3_sequential_circuit/tb_jkff_edge.vcd
$date
	Thu Sep 10 21:16:17 2026
$end
$version
	Icarus Verilog
$end
$timescale
	1ps
$end
$scope module tb_jkff_edge $end
$var wire 1 ! QN $end
$var wire 1 " Q $end
$var reg 1 # CLK $end
$var reg 1 $ J $end
$var reg 1 % K $end
$scope module uut $end
$var wire 1 # CLK $end
$var wire 1 $ J $end
$var wire 1 % K $end
$var wire 1 ! QN $end
$var reg 1 " Q $end
$upscope $end
$upscope $end
$enddefinitions $end
$comment Show the parameter values. $end
$dumpall
$end
#0
$dumpvars
0%
0$
0#
x"
x!
$end
#5000
1#
#10000
0#
#12000
1$
#15000
1#
#16000
0$
#20000
0#
#25000
1#
#26000
1%
#30000
0#
#35000
1!
0"
1#
#36000
1$
#40000
0#
#45000
0!
1"
1#
#50000
0#
#55000
1!
0"
1#
#56000
0$
#60000
0#
#65000
1#
#66000
0%
#67000
1$
#69000
0$
