module_6_7_FSM/mealy/practice_a/sequential_a.v
module mealy_fsm_AB (
    input  wire clk,
    input  wire rst,   // reset asynchronous, active high -> ke state P (A=0,B=0)
    input  wire X,
    output wire Z
);

    reg A, B;
    wire D_A, D_B;

    // Persamaan next-state hasil K-map (sudah diberikan di soal)
    assign D_A = B & X;
    assign D_B = (~X) | (~A & B & X);

    // Output logic (Mealy: bergantung state DAN input)
    assign Z = A & (~B) & (~X);

    always @(posedge clk or posedge rst) begin
        if (rst) begin
            A <= 1'b0;
            B <= 1'b0;
        end else begin
            A <= D_A;
            B <= D_B;
        end
    end

endmodule

module_6_7_FSM/mealy/practice_a/sequential_a_tb.v
`timescale 1ns/1ps

module tb_mealy_fsm_AB;

    reg clk, rst, X;
    wire Z;

    mealy_fsm_AB uut (
        .clk(clk),
        .rst(rst),
        .X(X),
        .Z(Z)
    );

    always #5 clk = ~clk;

    // Fungsi bantu untuk nama state (biar gampang dibaca)
    function [15:0] state_name;
        input a, b;
        begin
            case ({a,b})
                2'b00: state_name = "P ";
                2'b01: state_name = "Q ";
                2'b11: state_name = "R ";
                2'b10: state_name = "S ";
            endcase
        end
    endfunction

    initial begin
        clk = 0; rst = 1; X = 0;
        #10;
        rst = 0;

        // Urutan input untuk menelusuri P->Q->R->S->P dan memicu Z=1 di state S
        apply_x(1'b0); // P -> Q
        apply_x(1'b1); // Q -> R
        apply_x(1'b1); // R -> S
        apply_x(1'b0); // S -> Q, Z harus 1 di sini (state S, X=0)
        apply_x(1'b1); // Q -> R
        apply_x(1'b1); // R -> S
        apply_x(1'b1); // S -> P

        #20;
        $finish;
    end

    task apply_x(input x_val);
        begin
            X = x_val;
            @(posedge clk);
            #1;
            $display("t=%0t | State=%s | X=%b | Z=%b", $time, state_name(uut.A, uut.B), X, Z);
        end
    endtask

    initial begin
        $dumpfile("mealy_fsm.vcd");
        $dumpvars(0, tb_mealy_fsm_AB);
    end

endmodule

FPGA-Learning-Repository/module_6_7_FSM/mealy/practice_a/mealy_fsm.vcd
$date
	Thu Sep 17 10:26:06 2026
$end
$version
	Icarus Verilog
$end
$timescale
	1ps
$end
$scope module tb_mealy_fsm_AB $end
$var wire 1 ! Z $end
$var reg 1 " X $end
$var reg 1 # clk $end
$var reg 1 $ rst $end
$scope function state_name $end
$var reg 1 % a $end
$var reg 1 & b $end
$upscope $end
$scope module uut $end
$var wire 1 ' D_A $end
$var wire 1 ( D_B $end
$var wire 1 " X $end
$var wire 1 ! Z $end
$var wire 1 # clk $end
$var wire 1 $ rst $end
$var reg 1 ) A $end
$var reg 1 * B $end
$upscope $end
$scope task apply_x $end
$var reg 1 + x_val $end
$upscope $end
$upscope $end
$enddefinitions $end
$comment Show the parameter values. $end
$dumpall
$end
#0
$dumpvars
x+
0*
0)
1(
0'
x&
x%
1$
0#
0"
0!
$end
#5000
1#
#10000
0#
0+
0$
#15000
1*
1#
#16000
1'
1"
1+
0%
1&
#20000
0#
#25000
0(
1)
1#
#26000
1%
#30000
0#
#35000
0'
0*
1#
#36000
1(
1!
0"
0+
0&
#40000
0#
#45000
0!
1*
0)
1#
#46000
1'
1"
1+
0%
1&
#50000
0#
#55000
0(
1)
1#
#56000
1%
#60000
0#
#65000
0'
0*
1#
#66000
0&
#70000
0#
#75000
0)
1#
#76000
0%
