module_2_combinational_circuit/encoder.v
module priority_encoder4to2 (
    input wire [3:0] d,
    output reg [1:0] y,
    output reg valid // 1 when at least one input is active
);
    always @(*) begin
    valid = 1'b1;
    casez (d)
        4'b1???: y = 2'd3; // highest priority: d3
        4'b01??: y = 2'd2;
        4'b001?: y = 2'd1;
        4'b0001: y = 2'd0;
        default: begin y = 2'd0; valid = 1'b0; end // no input active
    endcase
    end
endmodule

FPGA-Learning-Repository/module_2_combinational_circuit/encoder_tb.v
`timescale 1ns / 1ps

module encoder_tb;

    reg [3:0] d;          
    wire [1:0] y;         
    wire valid;
    
    integer i;
    integer err = 0;      
    
    reg [1:0] ref_y;
    reg ref_valid;

    priority_encoder4to2 DUT (
        .d(d), 
        .y(y), 
        .valid(valid)
    );

    initial begin
        $dumpfile("encoder_tb.vcd"); // Untuk melihat waveform nanti
        $dumpvars(0, encoder_tb);

        $display("===== STAGE 2 : PRIORITY ENCODER (all 16 inputs) =====");
        $display("d3 d2 d1 d0 | y valid");
        $display("------------+---------");
        
        for (i = 0; i < 16; i = i + 1) begin
            d = i[3:0];
            #10;
            ref_valid = |d;
            
            if (d[3])      ref_y = 2'd3;
            else if (d[2]) ref_y = 2'd2;
            else if (d[1]) ref_y = 2'd1;
            else           ref_y = 2'd0;
            
            $display(" %b  %b  %b  %b | %b    %b", d[3], d[2], d[1], d[0], y, valid);
            
            if (y !== ref_y || valid !== ref_valid) begin
                err = err + 1;
                $display(" !! ERROR: Untuk input %b, dapat y=%b (seharusnya %b), valid=%b (seharusnya %b)", 
                        d, 
                        y, 
                        ref_y, 
                        valid, 
                        ref_valid);
            end
        end
        
        $display("----------------------");
        
        if (err == 0) 
            $display(">> PASS: all ENCODER tests behaved as expected.");
        else 
            $display(">> FAIL: %0d error(s) found.", err);
            
        $finish; 
    end
endmodule

FPGA-Learning-Repository/module_2_combinational_circuit/encoder_tb.vcd
$date
	Wed Sep  9 22:40:13 2026
$end
$version
	Icarus Verilog
$end
$timescale
	1ps
$end
$scope module encoder_tb $end
$var wire 2 ! y [1:0] $end
$var wire 1 " valid $end
$var reg 4 # d [3:0] $end
$var reg 1 $ ref_valid $end
$var reg 2 % ref_y [1:0] $end
$var integer 32 & err [31:0] $end
$var integer 32 ' i [31:0] $end
$scope module DUT $end
$var wire 4 ( d [3:0] $end
$var reg 1 " valid $end
$var reg 2 ) y [1:0] $end
$upscope $end
$upscope $end
$enddefinitions $end
$comment Show the parameter values. $end
$dumpall
$end
#0
$dumpvars
b0 )
b0 (
b0 '
b0 &
bx %
x$
b0 #
0"
b0 !
$end
#10000
1"
b1 #
b1 (
b1 '
b0 %
0$
#20000
b1 !
b1 )
b10 #
b10 (
b10 '
1$
#30000
b11 #
b11 (
b11 '
b1 %
#40000
b10 !
b10 )
b100 #
b100 (
b100 '
#50000
b101 #
b101 (
b101 '
b10 %
#60000
b110 #
b110 (
b110 '
#70000
b111 #
b111 (
b111 '
#80000
b11 !
b11 )
b1000 #
b1000 (
b1000 '
#90000
b1001 #
b1001 (
b1001 '
b11 %
#100000
b1010 #
b1010 (
b1010 '
#110000
b1011 #
b1011 (
b1011 '
#120000
b1100 #
b1100 (
b1100 '
#130000
b1101 #
b1101 (
b1101 '
#140000
b1110 #
b1110 (
b1110 '
#150000
b1111 #
b1111 (
b1111 '
#160000
b10000 '
