module_2_combinational_circuit/mux.v
module mux2to1_a (
    input wire a,
    input wire b,
    input wire sel,
    output wire y
);
assign y = sel ? b : a;
endmodule

module mux2to1_b (
    input wire a,
    input wire b,
    input wire sel,
    output reg y
);
always @(*) begin
    if (sel) y = b;
    else y = a;
end
endmodule

module mux4to1 (
    input wire [3:0] data,
    input wire [1:0] sel,
    output reg y
);
always @(*) begin
    case (sel)
        2'b00: y = data[0];
        2'b01: y = data[1];
        2'b10: y = data[2];
        2'b11: y = data[3];
        default: y = 1'b0;
    endcase
end
endmodule

FPGA-Learning-Repository/module_2_combinational_circuit/mux_tb.v
`timescale 1ns/1ps
module mux_tb;

    reg a1;
    reg b1;
    reg sel1;
    reg [3:0] data;
    reg [1:0] sel4;

    wire y_assign;
    wire y_ifelse;
    wire y4;

    mux2to1_a U_A (.a(a1), .b(b1), .sel(sel1), .y(y_assign));
    mux2to1_b U_B (.a(a1), .b(b1), .sel(sel1), .y(y_ifelse));
    mux4to1 U_4 (.data(data), .sel(sel4), .y(y4));

    integer i, err;
    initial begin 
        err = 0;
        $dumpfile("mux_tb.vcd");
        $dumpvars(0, mux_tb);

        $display("===== STAGE 1 : 2:1 MUX (assign vs if-else) =====");
        $display("sel a b | y_assign y_ifelse | ref");
        $display("--------+-------------------+-----");
        for (i = 0; i < 8; i = i + 1) begin
            {sel1, a1, b1} = i[2:0];
            #2;
            if (y_assign !== y_ifelse || y_assign !== (sel1 ? b1 : a1)) begin
                err = err + 1;
                $display("  !! mismatch at sel=%b a=%b b=%b", sel1, a1, b1);
            end
            $display(" %b %b %b |    %b        %b    |  %b",
                       sel1, a1, b1, y_assign, y_ifelse, (sel1 ? b1 : a1));
        end

        $display("");
        $display("===== STAGE 2 : basic 4:1 MUX (d = 1010) =====");
        $display("sel | d[3..0] | y");
        $display("----+---------+---");
        data = 4'b1010;
        for (i = 0; i < 4; i = i + 1) begin
            sel4 = i[1:0];
            #2;
            if (y4 !== data[sel4]) begin
                err = err + 1;
                $display("  !! mismatch at sel=%b", sel4);
            end
            $display(" %b  |  %b   | %b", sel4, data, y4);
        end

        $display("");
        $display("===== STAGE 3 : exhaustive 4:1 MUX (64 combinations) =====");
        for (i = 0; i < 64; i = i + 1) begin
            {sel4, data} = i[5:0];
            #2;
            if (y4 !== data[sel4]) begin
                err = err + 1;
                $display("  !! d=%b sel=%b : y=%b expected %b", data, sel4, y4, data[sel4]);
            end
        end
        $display("64 combinations checked against the reference y = d[sel].");

        if (err == 0)
            $display("\n>> PASS: all MUX tests behaved as expected.");
        else
            $display("\n>> FAIL: %0d mismatch(es) detected.", err);

        $finish;
    end
endmodule

FPGA-Learning-Repository/module_2_combinational_circuit/mux_tb.vcd
$date
	Wed Sep  9 22:25:25 2026
$end
$version
	Icarus Verilog
$end
$timescale
	1ps
$end
$scope module mux_tb $end
$var wire 1 ! y_ifelse $end
$var wire 1 " y_assign $end
$var wire 1 # y4 $end
$var reg 1 $ a1 $end
$var reg 1 % b1 $end
$var reg 4 & data [3:0] $end
$var reg 1 ' sel1 $end
$var reg 2 ( sel4 [1:0] $end
$var integer 32 ) err [31:0] $end
$var integer 32 * i [31:0] $end
$scope module U_4 $end
$var wire 4 + data [3:0] $end
$var wire 2 , sel [1:0] $end
$var reg 1 # y $end
$upscope $end
$scope module U_A $end
$var wire 1 $ a $end
$var wire 1 % b $end
$var wire 1 ' sel $end
$var wire 1 " y $end
$upscope $end
$scope module U_B $end
$var wire 1 $ a $end
$var wire 1 % b $end
$var wire 1 ' sel $end
$var reg 1 ! y $end
$upscope $end
$upscope $end
$enddefinitions $end
$comment Show the parameter values. $end
$dumpall
$end
#0
$dumpvars
bx ,
bx +
b0 *
b0 )
bx (
0'
bx &
0%
0$
x#
0"
0!
$end
#2000
1%
b1 *
#4000
1"
1!
1$
0%
b10 *
#6000
1%
b11 *
#8000
0"
0!
1'
0$
0%
b100 *
#10000
1"
1!
1%
b101 *
#12000
0"
0!
1$
0%
b110 *
#14000
1"
1!
1%
b111 *
#16000
0#
b0 (
b0 ,
b1010 &
b1010 +
b0 *
#18000
1#
b1 (
b1 ,
b1 *
#20000
0#
b10 (
b10 ,
b10 *
#22000
1#
b11 (
b11 ,
b11 *
#24000
0#
b0 (
b0 ,
b0 &
b0 +
b0 *
#26000
1#
b1 &
b1 +
b1 *
#28000
0#
b10 &
b10 +
b10 *
#30000
1#
b11 &
b11 +
b11 *
#32000
0#
b100 &
b100 +
b100 *
#34000
1#
b101 &
b101 +
b101 *
#36000
0#
b110 &
b110 +
b110 *
#38000
1#
b111 &
b111 +
b111 *
#40000
0#
b1000 &
b1000 +
b1000 *
#42000
1#
b1001 &
b1001 +
b1001 *
#44000
0#
b1010 &
b1010 +
b1010 *
#46000
1#
b1011 &
b1011 +
b1011 *
#48000
0#
b1100 &
b1100 +
b1100 *
#50000
1#
b1101 &
b1101 +
b1101 *
#52000
0#
b1110 &
b1110 +
b1110 *
#54000
1#
b1111 &
b1111 +
b1111 *
#56000
0#
b1 (
b1 ,
b0 &
b0 +
b10000 *
#58000
b1 &
b1 +
b10001 *
#60000
1#
b10 &
b10 +
b10010 *
#62000
b11 &
b11 +
b10011 *
#64000
0#
b100 &
b100 +
b10100 *
#66000
b101 &
b101 +
b10101 *
#68000
1#
b110 &
b110 +
b10110 *
#70000
b111 &
b111 +
b10111 *
#72000
0#
b1000 &
b1000 +
b11000 *
#74000
b1001 &
b1001 +
b11001 *
#76000
1#
b1010 &
b1010 +
b11010 *
#78000
b1011 &
b1011 +
b11011 *
#80000
0#
b1100 &
b1100 +
b11100 *
#82000
b1101 &
b1101 +
b11101 *
#84000
1#
b1110 &
b1110 +
b11110 *
#86000
b1111 &
b1111 +
b11111 *
#88000
0#
b10 (
b10 ,
b0 &
b0 +
b100000 *
#90000
b1 &
b1 +
b100001 *
#92000
b10 &
b10 +
b100010 *
#94000
b11 &
b11 +
b100011 *
#96000
1#
b100 &
b100 +
b100100 *
#98000
b101 &
b101 +
b100101 *
#100000
b110 &
b110 +
b100110 *
#102000
b111 &
b111 +
b100111 *
#104000
0#
b1000 &
b1000 +
b101000 *
#106000
b1001 &
b1001 +
b101001 *
#108000
b1010 &
b1010 +
b101010 *
#110000
b1011 &
b1011 +
b101011 *
#112000
1#
b1100 &
b1100 +
b101100 *
#114000
b1101 &
b1101 +
b101101 *
#116000
b1110 &
b1110 +
b101110 *
#118000
b1111 &
b1111 +
b101111 *
#120000
0#
b11 (
b11 ,
b0 &
b0 +
b110000 *
#122000
b1 &
b1 +
b110001 *
#124000
b10 &
b10 +
b110010 *
#126000
b11 &
b11 +
b110011 *
#128000
b100 &
b100 +
b110100 *
#130000
b101 &
b101 +
b110101 *
#132000
b110 &
b110 +
b110110 *
#134000
b111 &
b111 +
b110111 *
#136000
1#
b1000 &
b1000 +
b111000 *
#138000
b1001 &
b1001 +
b111001 *
#140000
b1010 &
b1010 +
b111010 *
#142000
b1011 &
b1011 +
b111011 *
#144000
b1100 &
b1100 +
b111100 *
#146000
b1101 &
b1101 +
b111101 *
#148000
b1110 &
b1110 +
b111110 *
#150000
b1111 &
b1111 +
b111111 *
#152000
b1000000 *
