module_4_shift_registers/dff_t.v
`timescale 1ns / 1ps
//======================================================================
//  dff_t.v  --  D flip-flop with a modelled clock-to-Q delay, and a
//               behavioural setup/hold checker
//----------------------------------------------------------------------
//  Module 4 : Sequential Circuit Practice I
//
//  dff_t              : rising-edge D flip-flop, asynchronous active-low
//                       reset, clock-to-Q delay TPD (ns). The delay makes
//                       timing VISIBLE and MEASURABLE in the waveform.
//  setup_hold_checker : watches a data input relative to the clock edge
//                       and reports every setup or hold violation. It is
//                       a simulation-only instrument (never synthesised).
//======================================================================

module dff_t #(
    parameter TPD = 1.0                 // clock-to-Q delay in ns
)(
    input  wire clk, rstn, d,
    output reg  q
);
    always @(posedge clk or negedge rstn)
        if (!rstn) q <= #TPD 1'b0;
        else       q <= #TPD d;          // intra-assignment delay
endmodule


module setup_hold_checker #(
    parameter real T_SETUP = 2.0,       // ns before the edge: d must be stable
    parameter real T_HOLD  = 1.0        // ns after the edge:  d must stay stable
)(
    input wire clk, d
);
    realtime t_d   = -1.0e9;            // time of the last change of d
    realtime t_clk = -1.0e9;            // time of the last rising clock edge
    integer  violations = 0;

    always @(d) begin
        t_d = $realtime;
        if (t_clk >= 0 && (t_d - t_clk) < T_HOLD) begin
            violations = violations + 1;
            $display("   !! HOLD  violation at %0t : d changed %0.1f ns after the edge (need %0.1f)",
                     $realtime, t_d - t_clk, T_HOLD);
        end
    end

    always @(posedge clk) begin
        t_clk = $realtime;
        if (t_d >= 0 && (t_clk - t_d) < T_SETUP) begin
            violations = violations + 1;
            $display("   !! SETUP violation at %0t : d changed %0.1f ns before the edge (need %0.1f)",
                     $realtime, t_clk - t_d, T_SETUP);
        end
    end
endmodule

module_5_counters/ripple_counter.v
`timescale 1ns / 1ps
//////////////////////////////////////////////////////////////////////////////////
// Company: 
// Engineer: 
// 
// Create Date: 09/14/2026 02:52:59 PM
// Design Name: 
// Module Name: ripple_counter
// Project Name: 
// Target Devices: 
// Tool Versions: 
// Description: 
// 
// Dependencies: 
// 
// Revision:
// Revision 0.01 - File Created
// Additional Comments:
// 
//////////////////////////////////////////////////////////////////////////////////


//====================================================
// T Flip-Flop
// Toggle FF: setiap clock, Q berubah kebalikannya
//====================================================

module t_ff(
    input wire clk,
    input wire rst,
    output reg q
);


always @(posedge clk or posedge rst)
begin

    if(rst)
        q <= 1'b0;

    else
        q <= ~q;

end


endmodule



//====================================================
// 3-bit Ripple Counter
//====================================================

module ripple_counter(

    input wire clk,
    input wire rst,

    output wire [2:0] q

);


// First flip flop
dff_t FF0 (
    .clk(clk),
    .rstn(rst),
    .d(~q[0]),
    .q(q[0])
);


// Second flip flop
dff_t FF1 (
    .clk(~q[0]),
    .rstn(rst),
    .d(~q[1]),
    .q(q[1])
);


// Third flip flop
dff_t FF2 (
    .clk(~q[1]),
    .rstn(rst),
    .d(~q[2]),
    .q(q[2])
);


endmodule

FPGA-Learning-Repository/module_5_counters/sync_counter.v
module sync_mod8 (input wire clk, rstn, output wire [2:0] q); 
    wire t0 = 1'b1; 
    wire t1 = q[0]; 
    wire t2 = q[0] & q[1]; 
    dff_t F0 (.clk(clk), .rstn(rstn), .d(q[0] ^ t0), .q(q[0])); 
    dff_t F1 (.clk(clk), .rstn(rstn), .d(q[1] ^ t1), .q(q[1])); 
    dff_t F2 (.clk(clk), .rstn(rstn), .d(q[2] ^ t2), .q(q[2])); 
endmodule

module sync_mod6 (input wire clk, rstn, output wire [2:0] q); 
    wire d0 = ~q[0]; 
    wire d1 = (q[1] ^ q[0]) & ~q[2]; 
    wire d2 = (q[1] & q[0]) | (q[2] & ~q[0]); 
    dff_t F0 (.clk(clk), .rstn(rstn), .d(d0), .q(q[0])); 
    dff_t F1 (.clk(clk), .rstn(rstn), .d(d1), .q(q[1])); 
    dff_t F2 (.clk(clk), .rstn(rstn), .d(d2), .q(q[2])); 
endmodule

module sync_bcd (input wire clk, rstn, output wire [3:0] q); 
    wire t0 = 1'b1; 
    wire t1 = ~q[3] & q[0]; 
    wire t2 =  q[1] & q[0]; 
    wire t3 = (q[3] & q[0]) | (q[2] & q[1] & q[0]); 
    dff_t F0 (.clk(clk), .rstn(rstn), .d(q[0] ^ t0), .q(q[0])); 
    dff_t F1 (.clk(clk), .rstn(rstn), .d(q[1] ^ t1), .q(q[1])); 
    dff_t F2 (.clk(clk), .rstn(rstn), .d(q[2] ^ t2), .q(q[2])); 
    dff_t F3 (.clk(clk), .rstn(rstn), .d(q[3] ^ t3), .q(q[3])); 
endmodule

FPGA-Learning-Repository/module_5_counters/timing_verification_tb.v
`timescale 1ns/1ps

module counter_timing_tb;

    // timing model parameters (Table 3.1 / WS-3 header)
    real TCQ    = 1.0;
    real TLOGIC = 1.5;
    real TSETUP = 2.0;

    reg clk = 0, rstn;
    wire [2:0] qs;   // synchronous
    wire [2:0] qr;   // ripple

    integer errors = 0;

    always #5 clk = ~clk;    // 10 ns period

    sync_mod8      S (.clk(clk), .rstn(rstn), .q(qs));
    ripple_counter R (.clk(clk), .rst(rstn), .q(qr));

    // decoder of state 0 on each bus
    wire dec0_s = (qs == 3'b000);
    wire dec0_r = (qr == 3'b000);

    // bit time stamps
    real ts0, ts1, ts2;
    real tr0, tr1, tr2;
    real edge_time;
    reg  measuring = 0;

    always @(qs[0]) if (measuring) ts0 = $realtime;
    always @(qs[1]) if (measuring) ts1 = $realtime;
    always @(qs[2]) if (measuring) ts2 = $realtime;

    always @(qr[0]) if (measuring) tr0 = $realtime;
    always @(qr[1]) if (measuring) tr1 = $realtime;
    always @(qr[2]) if (measuring) tr2 = $realtime;

    // states the ripple bus passes through
    integer  nstates = 0;
    reg [2:0] seen [0:7];
    always @(qr) if (measuring) begin
        if (nstates < 8) seen[nstates] = qr;
        nstates = nstates + 1;
    end

    // false pulse on the state-0 decoder
    real glitch_start;
    real glitch_width = 0.0;
    reg  glitch_seen = 0;
    always @(posedge dec0_r) if (measuring) glitch_start = $realtime;
    always @(negedge dec0_r) if (measuring) begin
        glitch_width = $realtime - glitch_start;
        glitch_seen  = 1;
    end

    integer i;
    real fmax_sync, fmax_r3, fmax_r8;

    initial begin
        $dumpfile("counter_timing_tb.vcd");
        $dumpvars(0, counter_timing_tb);

        rstn = 0;
        #8 rstn = 1;

        @(posedge clk);   // -> 1
        @(posedge clk);   // -> 2
        @(posedge clk);   // -> 3
        #5;               // settle at 40 ns, both buses = 011

        if (qs !== 3'b011) begin
            errors = errors + 1;
            $display("  !! setup: synchronous counter is %b, expected 011", qs);
        end
        if (qr !== 3'b011) begin
            errors = errors + 1;
            $display("  !! setup: ripple counter is %b, expected 011", qr);
        end

        measuring = 1;
        @(posedge clk);
        edge_time = $realtime;
        #10;
        measuring = 0;

        $display("===== PART A : SYNCHRONOUS COUNTER, transition 3 -> 4 =====");
        $display(" edge at %4.1f ns", edge_time);
        $display(" q[0] changed at %5.1f ns  (+%3.1f ns)", ts0, ts0 - edge_time);
        $display(" q[1] changed at %5.1f ns  (+%3.1f ns)", ts1, ts1 - edge_time);
        $display(" q[2] changed at %5.1f ns  (+%3.1f ns)", ts2, ts2 - edge_time);

        $display("\n===== PART B : RIPPLE COUNTER, same transition 3 -> 4 =====");
        $display(" q[0] changed at %5.1f ns  (+%3.1f ns)", tr0, tr0 - edge_time);
        $display(" q[1] changed at %5.1f ns  (+%3.1f ns)", tr1, tr1 - edge_time);
        $display(" q[2] changed at %5.1f ns  (+%3.1f ns)", tr2, tr2 - edge_time);
        $write(" intermediate states seen on the bus : 011");
        for (i = 0; i < nstates && i < 8; i = i + 1) $write(" -> %b", seen[i]);
        $write("\n");

        $display("\n===== PART C : DECODING GLITCH ON STATE 0 =====");
        if (glitch_seen)
            $display(" decoder of state 000 pulsed falsely at %4.1f ns for %3.1f ns",
                     glitch_start, glitch_width);
        else
            $display(" no false pulse detected");

        fmax_sync = 1000.0 / (TCQ + TLOGIC + TSETUP);
        fmax_r3   = 1000.0 / (3 * TCQ + TSETUP);
        fmax_r8   = 1000.0 / (8 * TCQ + TSETUP);
        $display("\n===== PART D : MAXIMUM CLOCK FREQUENCY =====");
        $display(" synchronous    : T = %3.1f ns -> f_max = %6.1f MHz", TCQ+TLOGIC+TSETUP, fmax_sync);
        $display(" ripple, 3 bits : T = %3.1f ns -> f_max = %6.1f MHz", 3*TCQ+TSETUP, fmax_r3);
        $display(" ripple, 8 bits : T = %3.1f ns -> f_max = %6.1f MHz", 8*TCQ+TSETUP, fmax_r8);

        $display("\n===== WS-3 TABLE VALUES =====");
        $display(" q[0] change time after the edge   | sync: +%3.1f ns | ripple: +%3.1f ns", ts0-edge_time, tr0-edge_time);
        $display(" q[1] change time after the edge   | sync: +%3.1f ns | ripple: +%3.1f ns", ts1-edge_time, tr1-edge_time);
        $display(" q[2] change time after the edge   | sync: +%3.1f ns | ripple: +%3.1f ns", ts2-edge_time, tr2-edge_time);
        $display(" intermediate states during 3->4   | sync: none      | ripple: 010, 000");
        $display(" decoder pulses on state 0         | sync: none      | ripple: %0.1f ns pulse", glitch_width);
        $display(" f_max (t_cq=1.0,t_logic=1.5,t_setup=2.0) | sync: %0.1f MHz | ripple(3-bit): %0.1f MHz",
                  fmax_sync, fmax_r3);

        if (errors == 0)
            $display("\n>> PASS: timing measurements behaved as expected.");
        else
            $display("\n>> FAIL: %0d problem(s) found.", errors);

        $finish;
    end
endmodule

module_5_counters/counter_timing_tb.vcd
$date
	Tue Sep 15 06:43:51 2026
$end
$version
	Icarus Verilog
$end
$timescale
	1ps
$end
$scope module counter_timing_tb $end
$var wire 3 ! qs [2:0] $end
$var wire 3 " qr [2:0] $end
$var wire 1 # dec0_s $end
$var wire 1 $ dec0_r $end
$var reg 1 % clk $end
$var reg 1 & glitch_seen $end
$var reg 1 ' measuring $end
$var reg 1 ( rstn $end
$var real 1 ) TCQ $end
$var real 1 * TLOGIC $end
$var real 1 + TSETUP $end
$var real 1 , edge_time $end
$var integer 32 - errors [31:0] $end
$var real 1 . fmax_r3 $end
$var real 1 / fmax_r8 $end
$var real 1 0 fmax_sync $end
$var real 1 1 glitch_start $end
$var real 1 2 glitch_width $end
$var integer 32 3 i [31:0] $end
$var integer 32 4 nstates [31:0] $end
$var real 1 5 tr0 $end
$var real 1 6 tr1 $end
$var real 1 7 tr2 $end
$var real 1 8 ts0 $end
$var real 1 9 ts1 $end
$var real 1 : ts2 $end
$scope module R $end
$var wire 1 % clk $end
$var wire 1 ( rst $end
$var wire 3 ; q [2:0] $end
$scope module FF0 $end
$var wire 1 % clk $end
$var wire 1 < d $end
$var wire 1 ( rstn $end
$var real 1 = TPD $end
$var reg 1 > q $end
$upscope $end
$scope module FF1 $end
$var wire 1 ? clk $end
$var wire 1 @ d $end
$var wire 1 ( rstn $end
$var real 1 A TPD $end
$var reg 1 B q $end
$upscope $end
$scope module FF2 $end
$var wire 1 C clk $end
$var wire 1 D d $end
$var wire 1 ( rstn $end
$var real 1 E TPD $end
$var reg 1 F q $end
$upscope $end
$upscope $end
$scope module S $end
$var wire 1 % clk $end
$var wire 1 ( rstn $end
$var wire 1 G t0 $end
$var wire 1 H t2 $end
$var wire 1 I t1 $end
$var wire 3 J q [2:0] $end
$scope module F0 $end
$var wire 1 % clk $end
$var wire 1 K d $end
$var wire 1 ( rstn $end
$var real 1 L TPD $end
$var reg 1 M q $end
$upscope $end
$scope module F1 $end
$var wire 1 % clk $end
$var wire 1 N d $end
$var wire 1 ( rstn $end
$var real 1 O TPD $end
$var reg 1 P q $end
$upscope $end
$scope module F2 $end
$var wire 1 % clk $end
$var wire 1 Q d $end
$var wire 1 ( rstn $end
$var real 1 R TPD $end
$var reg 1 S q $end
$upscope $end
$upscope $end
$upscope $end
$enddefinitions $end
$comment Show the parameter values. $end
$dumpall
r1 R
r1 O
r1 L
r1 E
r1 A
r1 =
$end
#0
$dumpvars
xS
xQ
xP
xN
xM
xK
bx J
xI
xH
1G
xF
xD
xC
xB
x@
x?
x>
x<
bx ;
r0 :
r0 9
r0 8
r0 7
r0 6
r0 5
b0 4
bx 3
r0 2
r0 1
r0 0
r0 /
r0 .
b0 -
r0 ,
r2 +
r1.5 *
r1 )
0(
0'
0&
0%
x$
x#
bx "
bx !
$end
#1000
0Q
1K
0N
0H
1?
1<
1C
1@
1D
0I
1#
0M
0P
b0 !
b0 J
0S
1$
0>
0B
b0 "
b0 ;
0F
#5000
1%
#8000
1(
#10000
0%
#15000
1%
#16000
0K
1N
0?
0<
1I
0#
b1 !
b1 J
1M
0$
b1 "
b1 ;
1>
#20000
0%
#25000
1%
#26000
1?
1<
1K
0I
1$
b0 "
b0 ;
0>
1P
0#
b10 !
b10 J
0M
#27000
0C
0@
0$
b10 "
b10 ;
1B
#30000
0%
#35000
1%
#36000
1Q
0K
1H
0N
0?
0<
1I
b11 !
b11 J
1M
b11 "
b11 ;
1>
#40000
1'
0%
#45000
r45 ,
1%
#46000
1?
1<
r46 5
r46 :
r46 9
1K
0H
r46 8
b1 4
0I
b10 "
b10 ;
0>
1S
0#
0P
b100 !
b100 J
0M
#47000
1C
1@
r47 6
r47 1
b10 4
1$
b0 "
b0 ;
0B
#48000
0D
r48 7
1&
r1 2
b11 4
0$
b100 "
b100 ;
1F
#50000
0%
#55000
1%
r100 /
r200 .
r222.2222222222222 0
b11 3
0'
