module_6_7_FSM/mealy/fsm/mealy_fsm.v
module mealy_1011_detector (
    input  wire clk,
    input  wire rst,
    input  wire X,
    output wire Z
);
    reg Q1, Q0;

    wire D1 = (~Q1 & Q0 & ~X) | (Q1 & ~Q0 & ~X) | (Q1 & Q0 & X);
    wire D0 = (~Q1 & Q0) | (Q1 & ~Q0) | (~Q0 & X);

    assign Z = Q1 & ~Q0 & X;

    always @(posedge clk or posedge rst) begin
        if (rst) begin
            Q1 <= 1'b0;
            Q0 <= 1'b0;
        end else begin
            Q1 <= D1;
            Q0 <= D0;
        end
    end
endmodule

module_6_7_FSM/mealy/fsm/mealy_fsm_tb.v
`timescale 1ns/1ps

module tb_mealy_1011_detector;
    reg clk, rst, X;
    wire Z;

    mealy_1011_detector uut (.clk(clk), .rst(rst), .X(X), .Z(Z));

    always #5 clk = ~clk;

    task apply_x(input b);
        begin
            X = b;
            @(posedge clk);
            #1;
            $display("t=%0t | Q1Q0=%b%b | X=%b | Z=%b", $time, uut.Q1, uut.Q0, X, Z);
        end
    endtask

    initial begin
        clk = 0; rst = 1; X = 0;
        #10; rst = 0;

        // Urutan: 1 0 1 1 0 1 1 -> uji overlap
        apply_x(1); // A0->A1
        apply_x(0); // A1->A2
        apply_x(1); // A2->A3
        apply_x(1); // A3->A1, Z HARUS 1 di baris ini
        apply_x(0); // A1->A2
        apply_x(1); // A2->A3
        apply_x(1); // A3->A1, Z HARUS 1 lagi (overlap)

        #20; $finish;
    end

    initial begin
        $dumpfile("mealy_1011.vcd");
        $dumpvars(0, tb_mealy_1011_detector);
    end
endmodule

FPGA-Learning-Repository/module_6_7_FSM/mealy/fsm/mealy_1011.vcd
$date
	Thu Sep 17 10:41:32 2026
$end
$version
	Icarus Verilog
$end
$timescale
	1ps
$end
$scope module tb_mealy_1011_detector $end
$var wire 1 ! Z $end
$var reg 1 " X $end
$var reg 1 # clk $end
$var reg 1 $ rst $end
$scope module uut $end
$var wire 1 % D0 $end
$var wire 1 & D1 $end
$var wire 1 " X $end
$var wire 1 ! Z $end
$var wire 1 # clk $end
$var wire 1 $ rst $end
$var reg 1 ' Q0 $end
$var reg 1 ( Q1 $end
$upscope $end
$scope task apply_x $end
$var reg 1 ) b $end
$upscope $end
$upscope $end
$enddefinitions $end
$comment Show the parameter values. $end
$dumpall
$end
#0
$dumpvars
x)
0(
0'
0&
0%
1$
0#
0"
0!
$end
#5000
1#
#10000
1%
0#
1"
1)
0$
#15000
1'
1#
#16000
1&
0"
0)
#20000
0#
#25000
0&
0%
1(
1#
#26000
1&
1"
1)
#30000
0#
#35000
1!
1%
0&
0'
1#
#40000
0#
#45000
0!
1'
0(
1#
#46000
1&
0"
0)
#50000
0#
#55000
0&
0%
1(
1#
#56000
1&
1"
1)
#60000
0#
#65000
1!
1%
0&
0'
1#
#70000
0#
#75000
0!
1'
0(
1#
