module_2_combinational_circuit/encoder.v
module priority_encoder4to2 (
    input wire [3:0] d,
    output reg [1:0] y,
    output reg valid // 1 when at least one input is active
);
    always @(*) begin
    valid = 1'b1;
    casez (d)
        4'b1???: y = 2'd3; // highest priority: d3
        4'b01??: y = 2'd2;
        4'b001?: y = 2'd1;
        4'b0001: y = 2'd0;
        default: begin y = 2'd0; valid = 1'b0; end // no input active
    endcase
    end
endmodule

module_2_combinational_circuit/decoder.v
module decoder2to4_case(
    input wire [1:0] a,
    input wire en,
    output reg [3:0] y
);
    always @(*) begin
        if (en)
            case(a)
                2'b00: y = 4'b0001;
                2'b01: y = 4'b0010;
                2'b10: y = 4'b0100;
                2'b11: y = 4'b1000;
                default: y = 4'b0000;
            endcase
        else
            y = 4'b0000;
    end
endmodule

module decoder2to4_shift(
    input wire [1:0] a,
    input wire en,
    output wire [3:0] y
);
    assign y = {4{en}} & (4'b0001 << a);
endmodule

module decoder3to8_shift(
    input wire [2:0] a,
    input wire en,
    output wire [7:0] y
);
    assign y = {8{en}} & (8'b0000_0001 << a);
endmodule

module decoder3to8_case(
    input wire [2:0] a,
    input wire en,
    output reg [7:0] y
);
    always @(*) begin
        if (en)
            case(a)
                3'b000: y = 8'b0000_0001;
                3'b001: y = 8'b0000_0010;
                3'b010: y = 8'b0000_0100;
                3'b011: y = 8'b0000_1000;
                3'b100: y = 8'b0001_0000;
                3'b101: y = 8'b0010_0000;
                3'b110: y = 8'b0100_0000;
                3'b111: y = 8'b1000_0000;
                default: y = 8'b0000_0000;
            endcase
        else
            y = 8'b0000_0000;
    end
endmodule

module_2_combinational_circuit/mux.v
module mux2to1_a (
    input wire a,
    input wire b,
    input wire sel,
    output wire y
);
assign y = sel ? b : a;
endmodule

module mux2to1_b (
    input wire a,
    input wire b,
    input wire sel,
    output reg y
);
always @(*) begin
    if (sel) y = b;
    else y = a;
end
endmodule

module mux4to1 (
    input wire [3:0] data,
    input wire [1:0] sel,
    output reg y
);
always @(*) begin
    case (sel)
        2'b00: y = data[0];
        2'b01: y = data[1];
        2'b10: y = data[2];
        2'b11: y = data[3];
        default: y = 1'b0;
    endcase
end
endmodule

modul2/demux.v
module demux1to2 (
    input wire din,
    input wire sel,
    output reg [1:0] y
);

    always @(*) begin
        y = 2'b00;
        case (sel)
            1'b0: y[0] = din;
            1'b1: y[1] = din;
        endcase
    end
endmodule

module demux1to4 (
    input wire din,
    input wire [1:0] sel,
    output reg [3:0] y
);
    always @(*) begin
        y = 4'b0000; // default first: every output defined
        case (sel)
            2'b00: y[0] = din; // then override the selected output
            2'b01: y[1] = din;
            2'b10: y[2] = din;
            2'b11: y[3] = din;
            default: y = 4'b0000;
        endcase
    end
endmodule

modul2/comb_system.v
module comb_system (
    input wire din,
    input wire [1:0] sel, code,
    input wire en,
    output wire dout,
    output wire [3:0] channel,
    output wire [1:0] code_back,
    output wire valid
);
    demux1to4 DM (.din(din), .sel(sel), .y(channel));
    mux4to1 MX (.data(channel), .sel(sel), .y(dout));
    wire [3:0] onehot; // link 2
    decoder2to4_shift DC (.a(code), .en(en), .y(onehot));
    priority_encoder4to2 PE (.d(onehot), .y(code_back), .valid(valid));
endmodule

module_2_combinational_circuit/comb_system_tb.v
`timescale 1ns / 1ps

module comb_system_tb;
    reg din;
    reg [1:0] sel;
    reg [1:0] code;
    reg en;
    
    wire dout;
    wire [3:0] channel;
    wire [1:0] code_back;
    wire valid;
    
    integer i;
    integer err = 0; 

    comb_system DUT (
        .din(din),
        .sel(sel),
        .code(code),
        .en(en),
        .dout(dout),
        .channel(channel),
        .code_back(code_back),
        .valid(valid)
    );

    initial begin
        $dumpfile("comb_system_tb.vcd");
        $dumpvars(0, comb_system_tb);
        
        $display("===== ROUND TRIPS: demux->mux and decoder->encoder (64 cases) =====");
        
        for (i = 0; i < 64; i = i + 1) begin
            {din, sel, code, en} = i[5:0];
            #10;

            if (dout !== din) begin
                err = err + 1;
                $display(" !! Link 1 ERROR: din=%b, tapi dout=%b", din, dout);
            end
            
            if (din == 1'b1 && channel !== (4'b0001 << sel)) begin
                err = err + 1;
                $display(" !! Link 1 ERROR: channel salah saat din=1, sel=%b, channel=%b", sel, channel);
            end else if (din == 1'b0 && channel !== 4'b0000) begin
                err = err + 1;
                $display(" !! Link 1 ERROR: channel tidak nol saat din=0, channel=%b", channel);
            end

            if (en == 1'b1 && (code_back !== code || valid !== 1'b1)) begin
                err = err + 1;
                $display(" !! Link 2 ERROR: en=1, code=%b, tapi code_back=%b, valid=%b", code, code_back, valid);
            end
            
            if (en == 1'b0 && valid !== 1'b0) begin
                err = err + 1;
                $display(" !! Link 2 ERROR: en=0, tapi valid=%b", valid);
            end
        end
        
        if (err == 0) begin
            $display("Link 1: dout equalled din on every case (demux -> mux).");
            $display("Link 2: code_back equalled code whenever en = 1 (decoder -> encoder).\n");
            $display(">> PASS: both round trips behaved as expected.");
        end else begin
            $display("\n>> FAIL: Ditemukan %0d error pada sistem kombinasi.", err);
        end
        
        $finish;
    end
endmodule

module_2_combinational_circuit/comb_system_tb.vcd
$date
	Wed Sep  9 22:48:41 2026
$end
$version
	Icarus Verilog
$end
$timescale
	1ps
$end
$scope module comb_system_tb $end
$var wire 1 ! valid $end
$var wire 1 " dout $end
$var wire 2 # code_back [1:0] $end
$var wire 4 $ channel [3:0] $end
$var reg 2 % code [1:0] $end
$var reg 1 & din $end
$var reg 1 ' en $end
$var reg 2 ( sel [1:0] $end
$var integer 32 ) err [31:0] $end
$var integer 32 * i [31:0] $end
$scope module DUT $end
$var wire 2 + code [1:0] $end
$var wire 1 & din $end
$var wire 1 ' en $end
$var wire 2 , sel [1:0] $end
$var wire 1 ! valid $end
$var wire 4 - onehot [3:0] $end
$var wire 1 " dout $end
$var wire 2 . code_back [1:0] $end
$var wire 4 / channel [3:0] $end
$scope module DC $end
$var wire 2 0 a [1:0] $end
$var wire 1 ' en $end
$var wire 4 1 y [3:0] $end
$upscope $end
$scope module DM $end
$var wire 1 & din $end
$var wire 2 2 sel [1:0] $end
$var reg 4 3 y [3:0] $end
$upscope $end
$scope module MX $end
$var wire 4 4 data [3:0] $end
$var wire 2 5 sel [1:0] $end
$var reg 1 " y $end
$upscope $end
$scope module PE $end
$var wire 4 6 d [3:0] $end
$var reg 1 ! valid $end
$var reg 2 7 y [1:0] $end
$upscope $end
$upscope $end
$upscope $end
$enddefinitions $end
$comment Show the parameter values. $end
$dumpall
$end
#0
$dumpvars
b0 7
b0 6
b0 5
b0 4
b0 3
b0 2
b0 1
b0 0
b0 /
b0 .
b0 -
b0 ,
b0 +
b0 *
b0 )
b0 (
0'
0&
b0 %
b0 $
b0 #
0"
0!
$end
#10000
1!
b1 -
b1 1
b1 6
1'
b1 *
#20000
0!
b0 -
b0 1
b0 6
b1 %
b1 +
b1 0
0'
b10 *
#30000
b1 #
b1 .
b1 7
1!
b10 -
b10 1
b10 6
1'
b11 *
#40000
0!
b0 #
b0 .
b0 7
b0 -
b0 1
b0 6
b10 %
b10 +
b10 0
0'
b100 *
#50000
b10 #
b10 .
b10 7
1!
b100 -
b100 1
b100 6
1'
b101 *
#60000
0!
b0 #
b0 .
b0 7
b0 -
b0 1
b0 6
b11 %
b11 +
b11 0
0'
b110 *
#70000
b11 #
b11 .
b11 7
1!
b1000 -
b1000 1
b1000 6
1'
b111 *
#80000
0!
b0 #
b0 .
b0 7
b0 -
b0 1
b0 6
b1 (
b1 ,
b1 2
b1 5
b0 %
b0 +
b0 0
0'
b1000 *
#90000
1!
b1 -
b1 1
b1 6
1'
b1001 *
#100000
0!
b0 -
b0 1
b0 6
b1 %
b1 +
b1 0
0'
b1010 *
#110000
b1 #
b1 .
b1 7
1!
b10 -
b10 1
b10 6
1'
b1011 *
#120000
0!
b0 #
b0 .
b0 7
b0 -
b0 1
b0 6
b10 %
b10 +
b10 0
0'
b1100 *
#130000
b10 #
b10 .
b10 7
1!
b100 -
b100 1
b100 6
1'
b1101 *
#140000
0!
b0 #
b0 .
b0 7
b0 -
b0 1
b0 6
b11 %
b11 +
b11 0
0'
b1110 *
#150000
b11 #
b11 .
b11 7
1!
b1000 -
b1000 1
b1000 6
1'
b1111 *
#160000
0!
b0 #
b0 .
b0 7
b0 -
b0 1
b0 6
b10 (
b10 ,
b10 2
b10 5
b0 %
b0 +
b0 0
0'
b10000 *
#170000
1!
b1 -
b1 1
b1 6
1'
b10001 *
#180000
0!
b0 -
b0 1
b0 6
b1 %
b1 +
b1 0
0'
b10010 *
#190000
b1 #
b1 .
b1 7
1!
b10 -
b10 1
b10 6
1'
b10011 *
#200000
0!
b0 #
b0 .
b0 7
b0 -
b0 1
b0 6
b10 %
b10 +
b10 0
0'
b10100 *
#210000
b10 #
b10 .
b10 7
1!
b100 -
b100 1
b100 6
1'
b10101 *
#220000
0!
b0 #
b0 .
b0 7
b0 -
b0 1
b0 6
b11 %
b11 +
b11 0
0'
b10110 *
#230000
b11 #
b11 .
b11 7
1!
b1000 -
b1000 1
b1000 6
1'
b10111 *
#240000
0!
b0 #
b0 .
b0 7
b0 -
b0 1
b0 6
b11 (
b11 ,
b11 2
b11 5
b0 %
b0 +
b0 0
0'
b11000 *
#250000
1!
b1 -
b1 1
b1 6
1'
b11001 *
#260000
0!
b0 -
b0 1
b0 6
b1 %
b1 +
b1 0
0'
b11010 *
#270000
b1 #
b1 .
b1 7
1!
b10 -
b10 1
b10 6
1'
b11011 *
#280000
0!
b0 #
b0 .
b0 7
b0 -
b0 1
b0 6
b10 %
b10 +
b10 0
0'
b11100 *
#290000
b10 #
b10 .
b10 7
1!
b100 -
b100 1
b100 6
1'
b11101 *
#300000
0!
b0 #
b0 .
b0 7
b0 -
b0 1
b0 6
b11 %
b11 +
b11 0
0'
b11110 *
#310000
b11 #
b11 .
b11 7
1!
b1000 -
b1000 1
b1000 6
1'
b11111 *
#320000
1"
0!
b0 #
b0 .
b0 7
b1 $
b1 /
b1 3
b1 4
b0 -
b0 1
b0 6
1&
b0 (
b0 ,
b0 2
b0 5
b0 %
b0 +
b0 0
0'
b100000 *
#330000
1!
b1 -
b1 1
b1 6
1'
b100001 *
#340000
0!
b0 -
b0 1
b0 6
b1 %
b1 +
b1 0
0'
b100010 *
#350000
b1 #
b1 .
b1 7
1!
b10 -
b10 1
b10 6
1'
b100011 *
#360000
0!
b0 #
b0 .
b0 7
b0 -
b0 1
b0 6
b10 %
b10 +
b10 0
0'
b100100 *
#370000
b10 #
b10 .
b10 7
1!
b100 -
b100 1
b100 6
1'
b100101 *
#380000
0!
b0 #
b0 .
b0 7
b0 -
b0 1
b0 6
b11 %
b11 +
b11 0
0'
b100110 *
#390000
b11 #
b11 .
b11 7
1!
b1000 -
b1000 1
b1000 6
1'
b100111 *
#400000
0!
b0 #
b0 .
b0 7
b10 $
b10 /
b10 3
b10 4
1"
b0 -
b0 1
b0 6
b1 (
b1 ,
b1 2
b1 5
b0 %
b0 +
b0 0
0'
b101000 *
#410000
1!
b1 -
b1 1
b1 6
1'
b101001 *
#420000
0!
b0 -
b0 1
b0 6
b1 %
b1 +
b1 0
0'
b101010 *
#430000
b1 #
b1 .
b1 7
1!
b10 -
b10 1
b10 6
1'
b101011 *
#440000
0!
b0 #
b0 .
b0 7
b0 -
b0 1
b0 6
b10 %
b10 +
b10 0
0'
b101100 *
#450000
b10 #
b10 .
b10 7
1!
b100 -
b100 1
b100 6
1'
b101101 *
#460000
0!
b0 #
b0 .
b0 7
b0 -
b0 1
b0 6
b11 %
b11 +
b11 0
0'
b101110 *
#470000
b11 #
b11 .
b11 7
1!
b1000 -
b1000 1
b1000 6
1'
b101111 *
#480000
0!
b0 #
b0 .
b0 7
b100 $
b100 /
b100 3
b100 4
1"
b0 -
b0 1
b0 6
b10 (
b10 ,
b10 2
b10 5
b0 %
b0 +
b0 0
0'
b110000 *
#490000
1!
b1 -
b1 1
b1 6
1'
b110001 *
#500000
0!
b0 -
b0 1
b0 6
b1 %
b1 +
b1 0
0'
b110010 *
#510000
b1 #
b1 .
b1 7
1!
b10 -
b10 1
b10 6
1'
b110011 *
#520000
0!
b0 #
b0 .
b0 7
b0 -
b0 1
b0 6
b10 %
b10 +
b10 0
0'
b110100 *
#530000
b10 #
b10 .
b10 7
1!
b100 -
b100 1
b100 6
1'
b110101 *
#540000
0!
b0 #
b0 .
b0 7
b0 -
b0 1
b0 6
b11 %
b11 +
b11 0
0'
b110110 *
#550000
b11 #
b11 .
b11 7
1!
b1000 -
b1000 1
b1000 6
1'
b110111 *
#560000
0!
b0 #
b0 .
b0 7
b1000 $
b1000 /
b1000 3
b1000 4
1"
b0 -
b0 1
b0 6
b11 (
b11 ,
b11 2
b11 5
b0 %
b0 +
b0 0
0'
b111000 *
#570000
1!
b1 -
b1 1
b1 6
1'
b111001 *
#580000
0!
b0 -
b0 1
b0 6
b1 %
b1 +
b1 0
0'
b111010 *
#590000
b1 #
b1 .
b1 7
1!
b10 -
b10 1
b10 6
1'
b111011 *
#600000
0!
b0 #
b0 .
b0 7
b0 -
b0 1
b0 6
b10 %
b10 +
b10 0
0'
b111100 *
#610000
b10 #
b10 .
b10 7
1!
b100 -
b100 1
b100 6
1'
b111101 *
#620000
0!
b0 #
b0 .
b0 7
b0 -
b0 1
b0 6
b11 %
b11 +
b11 0
0'
b111110 *
#630000
b11 #
b11 .
b11 7
1!
b1000 -
b1000 1
b1000 6
1'
b111111 *
#640000
b1000000 *
