module_2_combinational_circuit/decoder.v
module decoder2to4_case(
    input wire [1:0] a,
    input wire en,
    output reg [3:0] y
);
    always @(*) begin
        if (en)
            case(a)
                2'b00: y = 4'b0001;
                2'b01: y = 4'b0010;
                2'b10: y = 4'b0100;
                2'b11: y = 4'b1000;
                default: y = 4'b0000;
            endcase
        else
            y = 4'b0000;
    end
endmodule

module decoder2to4_shift(
    input wire [1:0] a,
    input wire en,
    output wire [3:0] y
);
    assign y = {4{en}} & (4'b0001 << a);
endmodule

module decoder3to8_shift(
    input wire [2:0] a,
    input wire en,
    output wire [7:0] y
);
    assign y = {8{en}} & (8'b0000_0001 << a);
endmodule

module decoder3to8_case(
    input wire [2:0] a,
    input wire en,
    output reg [7:0] y
);
    always @(*) begin
        if (en)
            case(a)
                3'b000: y = 8'b0000_0001;
                3'b001: y = 8'b0000_0010;
                3'b010: y = 8'b0000_0100;
                3'b011: y = 8'b0000_1000;
                3'b100: y = 8'b0001_0000;
                3'b101: y = 8'b0010_0000;
                3'b110: y = 8'b0100_0000;
                3'b111: y = 8'b1000_0000;
                default: y = 8'b0000_0000;
            endcase
        else
            y = 8'b0000_0000;
    end
endmodule

FPGA-Learning-Repository/module_2_combinational_circuit/decoder_tb.v
`timescale 1ns/1ps
module decoder_tb;

    reg [1:0] a1;
    reg [2:0] a2;

    reg en1;
    reg en2;

    wire [3:0] y1_case;
    wire [3:0] y1_shift;
    wire [7:0] y2_case;
    wire [7:0] y2_shift;

    decoder2to4_shift U_2TO4_SHIFT(.a(a1), .en(en1), .y(y1_shift));
    decoder2to4_case U_2TO4_CASE(.a(a1), .en(en1), .y(y1_case));
    decoder3to8_shift U__3TO8_SHIFT(.a(a2), .en(en2), .y(y2_shift));
    decoder3to8_case U__3TO8_CASE(.a(a2), .en(en2), .y(y2_case));

    integer i, err;
    initial begin
        err = 0;
        $dumpfile("decoder_tb.vcd");
        $dumpvars(0, decoder_tb);

        $display("===== 2-to-4 DECODER (8 combinations) =====");
        $display("en a1 a0 | y3 y2 y1 y0");
        $display("---------+-------------");

        for (i = 0; i < 8; i = i + 1) begin
            {a1, en1} = i[2:0];
            #2;

            if (y1_case !== (en1 ? (4'b0001 << a1) : 4'b0000)) begin
                err = err + 1;
                $display("  !! decoder 2-to-4 mismatch at en=%b a=%b", 
                    en1, 
                    a1);
            end

            if (en1 && (y1_case[3] + y1_case[2] + y1_case[1] + y1_case[0]) != 1) begin
                err = err + 1;
                $display("  !! decoder 2-to-4 one-hot property violation at en=%b a=%b", 
                    en1, 
                    a1);
            end

            if (y1_case !== y1_shift) begin
                err = err + 1;
                $display("  !! decoder 2-to-4 style mismatch at en=%b a=%b : shift=%b while case=%b",
                    en1, 
                    a1, 
                    y1_shift, 
                    y1_case);
            end

            $display("%b  %b  %b  | %b  %b  %b  %b ", 
                    en1,
                    a1[1],
                    a1[0],
                    y1_case[3],
                    y1_case[2],
                    y1_case[1],
                    y1_case[0]);
        end

        $display("");
        $display("===== 3-to-8 DECODER (16 combinations) =====");
        $display("en a2a1a0 | y (case) | y (shift)");
        $display("----------+----------+----------");
        for (i = 0; i < 16; i = i + 1) begin
            {a2, en2} = i[3:0];
            #2;

            if (y2_shift !== (en2 ? (8'b0000_0001 << a2) : 8'b0000_0000)) begin
                err = err + 1;
                $display("  !! decoder 3-to-8 mismatch at en=%b a=%b", 
                    en2, 
                    a2);
            end

            if (en2 && (y2_shift[7] + y2_shift[6] + y2_shift[5] + y2_shift[4] +
                        y2_shift[3] + y2_shift[2] + y2_shift[1] + y2_shift[8]) != 1) begin
                err = err + 1;
                $display("  !! decoder 3-to-8 one-hot property violation at en=%b a=%b", 
                    en2, 
                    a2);
            end

            if (y2_case !== y2_shift) begin
                err = err + 1;
                $display("  !! decoder 3-to-8 style mismatch at en=%b a=%b : shift=%b while case=%b",
                    en2, 
                    a2, 
                    y2_shift, 
                    y2_case);
            end

            $display("%b   %b%b%b   | %b%b%b%b%b%b%b%b | %b%b%b%b%b%b%b%b",
                    en2,
                    a2[2],
                    a2[1],
                    a2[0],
                    y2_case[7],
                    y2_case[6],
                    y2_case[5],
                    y2_case[4],
                    y2_case[3],
                    y2_case[2],
                    y2_case[1],
                    y2_case[0],
                    y2_shift[7],
                    y2_shift[6],
                    y2_shift[5],
                    y2_shift[4],
                    y2_shift[3],
                    y2_shift[2],
                    y2_shift[1],
                    y2_shift[0]);
        end

        if (err == 0)
            $display("\n>> PASS: all DECODER tests behaved as expected.");
        
        else
            $display("\n>> FAIL: %0d mismatch(es) detected.", err);

        $finish;
    end
endmodule

module_2_combinational_circuit/decoder_tb.vcd
$date
	Wed Sep  9 22:06:43 2026
$end
$version
	Icarus Verilog
$end
$timescale
	1ps
$end
$scope module decoder_tb $end
$var wire 8 ! y2_shift [7:0] $end
$var wire 8 " y2_case [7:0] $end
$var wire 4 # y1_shift [3:0] $end
$var wire 4 $ y1_case [3:0] $end
$var reg 2 % a1 [1:0] $end
$var reg 3 & a2 [2:0] $end
$var reg 1 ' en1 $end
$var reg 1 ( en2 $end
$var integer 32 ) err [31:0] $end
$var integer 32 * i [31:0] $end
$scope module U_2TO4_CASE $end
$var wire 2 + a [1:0] $end
$var wire 1 ' en $end
$var reg 4 , y [3:0] $end
$upscope $end
$scope module U_2TO4_SHIFT $end
$var wire 2 - a [1:0] $end
$var wire 1 ' en $end
$var wire 4 . y [3:0] $end
$upscope $end
$scope module U__3TO8_CASE $end
$var wire 3 / a [2:0] $end
$var wire 1 ( en $end
$var reg 8 0 y [7:0] $end
$upscope $end
$scope module U__3TO8_SHIFT $end
$var wire 3 1 a [2:0] $end
$var wire 1 ( en $end
$var wire 8 2 y [7:0] $end
$upscope $end
$upscope $end
$enddefinitions $end
$comment Show the parameter values. $end
$dumpall
$end
#0
$dumpvars
bx 2
bx 1
bx 0
bx /
b0 .
b0 -
b0 ,
b0 +
b0 *
b0 )
x(
0'
bx &
b0 %
b0 $
b0 #
bx "
bx !
$end
#2000
b1 $
b1 ,
b1 #
b1 .
1'
b1 *
#4000
b0 $
b0 ,
b0 #
b0 .
b1 %
b1 +
b1 -
0'
b10 *
#6000
b10 $
b10 ,
b10 #
b10 .
1'
b11 *
#8000
b0 $
b0 ,
b0 #
b0 .
b10 %
b10 +
b10 -
0'
b100 *
#10000
b100 $
b100 ,
b100 #
b100 .
1'
b101 *
#12000
b0 $
b0 ,
b0 #
b0 .
b11 %
b11 +
b11 -
0'
b110 *
#14000
b1000 $
b1000 ,
b1000 #
b1000 .
1'
b111 *
#16000
b0 "
b0 0
b0 !
b0 2
b0 &
b0 /
b0 1
0(
b0 *
#18000
b1 "
b1 0
b1 !
b1 2
1(
b1 *
#20000
b0 "
b0 0
b0 !
b0 2
b1 &
b1 /
b1 1
0(
b10 *
#22000
b10 "
b10 0
b10 !
b10 2
1(
b11 *
#24000
b0 "
b0 0
b0 !
b0 2
b10 &
b10 /
b10 1
0(
b100 *
#26000
b100 "
b100 0
b100 !
b100 2
1(
b101 *
#28000
b0 "
b0 0
b0 !
b0 2
b11 &
b11 /
b11 1
0(
b110 *
#30000
b1000 "
b1000 0
b1000 !
b1000 2
1(
b111 *
#32000
b0 "
b0 0
b0 !
b0 2
b100 &
b100 /
b100 1
0(
b1000 *
#34000
b10000 "
b10000 0
b10000 !
b10000 2
1(
b1001 *
#36000
b0 "
b0 0
b0 !
b0 2
b101 &
b101 /
b101 1
0(
b1010 *
#38000
b100000 "
b100000 0
b100000 !
b100000 2
1(
b1011 *
#40000
b0 "
b0 0
b0 !
b0 2
b110 &
b110 /
b110 1
0(
b1100 *
#42000
b1000000 "
b1000000 0
b1000000 !
b1000000 2
1(
b1101 *
#44000
b0 "
b0 0
b0 !
b0 2
b111 &
b111 /
b111 1
0(
b1110 *
#46000
b10000000 "
b10000000 0
b10000000 !
b10000000 2
1(
b1111 *
#48000
b10000 *
