modul2/demux.v
module demux1to2 (
    input wire din,
    input wire sel,
    output reg [1:0] y
);

    always @(*) begin
        y = 2'b00;
        case (sel)
            1'b0: y[0] = din;
            1'b1: y[1] = din;
        endcase
    end
endmodule

module demux1to4 (
    input wire din,
    input wire [1:0] sel,
    output reg [3:0] y
);
    always @(*) begin
        y = 4'b0000; // default first: every output defined
        case (sel)
            2'b00: y[0] = din; // then override the selected output
            2'b01: y[1] = din;
            2'b10: y[2] = din;
            2'b11: y[3] = din;
            default: y = 4'b0000;
        endcase
    end
endmodule

modul2/demux_tb.v
`timescale 1ns/1ps
module demux_tb;

    reg din2;
    reg sel2;
    reg din4;
    reg [1:0] sel4;

    wire [1:0] y2;
    wire [3:0] y4;

    demux1to2 U_2(.din(din2), .sel(sel2), .y(y2));
    demux1to4 U_4(.din(din4), .sel(sel4), .y(y4));

    integer i, err;
    initial begin
        err = 0;
        $dumpfile("demux_tb.vcd");
        $dumpvars(0, demux_tb);

        $display("===== 1-to-2 DEMUX (4 combinations) =====");
        $display("sel din | y1 y0");
        $display("--------+------");
        for (i = 0; i < 4; i = i + 1) begin
            {sel2, din2} = i[1:0];
            #2;
            if (y2 !== (din2 ? (2'b01 << sel2) : 2'b0) ) begin
                err = err + 1;
                $display("  !! mismatch at sel=%b din=%b", sel2, din2);
            end
            $display(" %b   %b  |  %b  %b", sel2, din2, y2[1], y2[0]);
        end

        $display("");
        $display("===== 1-to-4 DEMUX (8 combinations) =====");
        $display("sel din | y3 y2 y1 y0");
        $display("--------+------------");
        for (i = 0; i < 8; i = i + 1) begin
            {sel4, din4} = i[2:0];
            #2;
            if (y4 !== (din4 ? (4'b0001 << sel4) : 4'b0000)) begin
                err = err + 1;
                $display("  !! mismatch at sel=%b din=%b", sel4, din4);
            end
            $display("%b   %b  |  %b  %b  %b  %b", sel4, din4, y4[3], y4[2], y4[1], y4[0]);
        end

        if (err == 0)
            $display("\n>> PASS: all DEMUX tests behaved as expected.");

        else
            $display("\n>> FAIL: %0d mismatch(es) detected.", err);

        $finish;
    end
endmodule

module_2_combinational_circuit/demux_tb.vcd
$date
	Wed Sep  9 22:28:00 2026
$end
$version
	Icarus Verilog
$end
$timescale
	1ps
$end
$scope module demux_tb $end
$var wire 4 ! y4 [3:0] $end
$var wire 2 " y2 [1:0] $end
$var reg 1 # din2 $end
$var reg 1 $ din4 $end
$var reg 1 % sel2 $end
$var reg 2 & sel4 [1:0] $end
$var integer 32 ' err [31:0] $end
$var integer 32 ( i [31:0] $end
$scope module U_2 $end
$var wire 1 # din $end
$var wire 1 % sel $end
$var reg 2 ) y [1:0] $end
$upscope $end
$scope module U_4 $end
$var wire 1 $ din $end
$var wire 2 * sel [1:0] $end
$var reg 4 + y [3:0] $end
$upscope $end
$upscope $end
$enddefinitions $end
$comment Show the parameter values. $end
$dumpall
$end
#0
$dumpvars
bx +
bx *
b0 )
b0 (
b0 '
bx &
0%
x$
0#
b0 "
bx !
$end
#2000
b1 "
b1 )
1#
b1 (
#4000
b0 "
b0 )
1%
0#
b10 (
#6000
b10 "
b10 )
1#
b11 (
#8000
b0 !
b0 +
b0 &
b0 *
0$
b0 (
#10000
b1 !
b1 +
1$
b1 (
#12000
b0 !
b0 +
b1 &
b1 *
0$
b10 (
#14000
b10 !
b10 +
1$
b11 (
#16000
b0 !
b0 +
b10 &
b10 *
0$
b100 (
#18000
b100 !
b100 +
1$
b101 (
#20000
b0 !
b0 +
b11 &
b11 *
0$
b110 (
#22000
b1000 !
b1000 +
1$
b111 (
#24000
b1000 (
