FPGA-Learning-Repository/module_5_counters/assignment1/counter_00_60.v
module counter_00_60 (
    input  wire       clk,    // system clock
    input  wire       rstn,   // asynchronous reset, active low
    input  wire       en,     // count enable
    output reg  [3:0] ones,   // ones digit, 0..9
    output reg  [3:0] tens,   // tens digit, 0..6
    output wire       tc      // terminal count: currently at 60
);
    assign tc = en & (tens == 4'd6) & (ones == 4'd0);

    always @(posedge clk or negedge rstn) begin
        if (!rstn) begin
            ones <= 4'd0;
            tens <= 4'd0;
        end
        else if (en) begin
            if (tens == 4'd6 && ones == 4'd0) begin // already 60 -> back to 00
                ones <= 4'd0;
                tens <= 4'd0;
            end
            else if (ones == 4'd9) begin             // ones full -> carry to tens
                ones <= 4'd0;
                tens <= tens + 4'd1;
            end
            else begin                               // ordinary increment
                ones <= ones + 4'd1;
            end
        end
    end
endmodule

module_5_counters/assignment1/counter_00_60_tb.v
`timescale 1ns/1ps

module counter_00_60_tb;
    reg clk = 0, rstn, en;
    wire [3:0] ones, tens;
    wire tc;
    integer errors = 0;
    integer i, n, value;

    // 100 MHz-style clock, period doesn't matter functionally here
    always #5 clk = ~clk;

    counter_00_60 DUT (
        .clk(clk), .rstn(rstn), .en(en),
        .ones(ones), .tens(tens), .tc(tc)
    );

    task tick;
        begin
            @(posedge clk); #1;
        end
    endtask

    task reset;
        begin
            @(negedge clk); rstn = 0; #2; rstn = 1;
        end
    endtask

    // advance the counter (en must be 1) until tens*10+ones == target
    task run_to(input integer target);
        begin
            while ((tens*10 + ones) !== target) tick();
        end
    endtask

    initial begin
        $dumpfile("counter_00_60_tb.vcd");
        $dumpvars(0, counter_00_60_tb);

        en = 1;

        $display("===== STAGE 1 : RESET =====");
        reset();
        $display(" after reset : %02d", tens*10 + ones);

        $display("\n===== STAGE 2 : TWO COMPLETE CYCLES (122 counts) =====");
        n = 0;
        for (i = 1; i <= 122; i = i + 1) begin
            tick();
            n = (n + 1) % 61;
            value = tens*10 + ones;
            if (value !== n) begin
                errors = errors + 1;
                $display("  !! count %0d : read %0d, expected %0d", i, value, n);
            end
            if (ones > 9 || tens > 6) begin
                errors = errors + 1;
                $display("  !! output is not valid BCD : tens=%0d ones=%0d", tens, ones);
            end
        end
        $display(" 122 counts matched the reference (n+1) mod 61; all outputs valid BCD.");

        $display("\n===== STAGE 3 : CRITICAL TRANSITIONS =====");
        run_to(9);
        tick();
        $display(" 09 -> %02d", tens*10 + ones);
        run_to(59);
        tick();
        $display(" 59 -> %02d", tens*10 + ones);
        tick();
        $display(" 60 -> %02d", tens*10 + ones);

        $display("\n===== STAGE 4 : ENABLE = 0 HOLDS THE COUNT =====");
        run_to(5);
        $display(" value before holding : %02d", tens*10 + ones);
        en = 0;
        for (i = 0; i < 4; i = i + 1) tick();
        $display(" after 4 clocks with en=0 : %02d", tens*10 + ones);
        en = 1;
        tick();
        $display(" after en=1 again : %02d", tens*10 + ones);

        $display("\n===== STAGE 5 : TERMINAL COUNT =====");
        run_to(60);
        $display(" value = %02d, tc = %b", tens*10 + ones, tc);
        tick();
        $display(" one clock later = %02d, tc = %b", tens*10 + ones, tc);

        if (errors == 0)
            $display("\n>> PASS: the 00-60 counter meets its specification.");
        else
            $display("\n>> FAIL: %0d error(s) found.", errors);

        $finish;
    end
endmodule

module_5_counters/assignment1/counter_00_60_tb.vcd
$date
	Mon Sep 14 15:18:01 2026
$end
$version
	Icarus Verilog
$end
$timescale
	1ps
$end
$scope module counter_00_60_tb $end
$var wire 4 ! tens [3:0] $end
$var wire 1 " tc $end
$var wire 4 # ones [3:0] $end
$var reg 1 $ clk $end
$var reg 1 % en $end
$var reg 1 & rstn $end
$var integer 32 ' errors [31:0] $end
$var integer 32 ( i [31:0] $end
$var integer 32 ) n [31:0] $end
$var integer 32 * value [31:0] $end
$scope module DUT $end
$var wire 1 $ clk $end
$var wire 1 % en $end
$var wire 1 & rstn $end
$var wire 1 " tc $end
$var reg 4 + ones [3:0] $end
$var reg 4 , tens [3:0] $end
$upscope $end
$scope task reset $end
$upscope $end
$scope task run_to $end
$var integer 32 - target [31:0] $end
$upscope $end
$scope task tick $end
$upscope $end
$upscope $end
$enddefinitions $end
$comment Show the parameter values. $end
$dumpall
$end
#0
$dumpvars
bx -
bx ,
bx +
bx *
bx )
bx (
b0 '
x&
1%
0$
bx #
x"
bx !
$end
#5000
1$
#10000
0"
b0 !
b0 ,
b0 #
b0 +
0&
0$
#12000
b1 (
b0 )
1&
#15000
b1 #
b1 +
1$
#16000
b10 (
b1 *
b1 )
#20000
0$
#25000
b10 #
b10 +
1$
#26000
b11 (
b10 *
b10 )
#30000
0$
#35000
b11 #
b11 +
1$
#36000
b100 (
b11 *
b11 )
#40000
0$
#45000
b100 #
b100 +
1$
#46000
b101 (
b100 *
b100 )
#50000
0$
#55000
b101 #
b101 +
1$
#56000
b110 (
b101 *
b101 )
#60000
0$
#65000
b110 #
b110 +
1$
#66000
b111 (
b110 *
b110 )
#70000
0$
#75000
b111 #
b111 +
1$
#76000
b1000 (
b111 *
b111 )
#80000
0$
#85000
b1000 #
b1000 +
1$
#86000
b1001 (
b1000 *
b1000 )
#90000
0$
#95000
b1001 #
b1001 +
1$
#96000
b1010 (
b1001 *
b1001 )
#100000
0$
#105000
b1 !
b1 ,
b0 #
b0 +
1$
#106000
b1011 (
b1010 *
b1010 )
#110000
0$
#115000
b1 #
b1 +
1$
#116000
b1100 (
b1011 *
b1011 )
#120000
0$
#125000
b10 #
b10 +
1$
#126000
b1101 (
b1100 *
b1100 )
#130000
0$
#135000
b11 #
b11 +
1$
#136000
b1110 (
b1101 *
b1101 )
#140000
0$
#145000
b100 #
b100 +
1$
#146000
b1111 (
b1110 *
b1110 )
#150000
0$
#155000
b101 #
b101 +
1$
#156000
b10000 (
b1111 *
b1111 )
#160000
0$
#165000
b110 #
b110 +
1$
#166000
b10001 (
b10000 *
b10000 )
#170000
0$
#175000
b111 #
b111 +
1$
#176000
b10010 (
b10001 *
b10001 )
#180000
0$
#185000
b1000 #
b1000 +
1$
#186000
b10011 (
b10010 *
b10010 )
#190000
0$
#195000
b1001 #
b1001 +
1$
#196000
b10100 (
b10011 *
b10011 )
#200000
0$
#205000
b10 !
b10 ,
b0 #
b0 +
1$
#206000
b10101 (
b10100 *
b10100 )
#210000
0$
#215000
b1 #
b1 +
1$
#216000
b10110 (
b10101 *
b10101 )
#220000
0$
#225000
b10 #
b10 +
1$
#226000
b10111 (
b10110 *
b10110 )
#230000
0$
#235000
b11 #
b11 +
1$
#236000
b11000 (
b10111 *
b10111 )
#240000
0$
#245000
b100 #
b100 +
1$
#246000
b11001 (
b11000 *
b11000 )
#250000
0$
#255000
b101 #
b101 +
1$
#256000
b11010 (
b11001 *
b11001 )
#260000
0$
#265000
b110 #
b110 +
1$
#266000
b11011 (
b11010 *
b11010 )
#270000
0$
#275000
b111 #
b111 +
1$
#276000
b11100 (
b11011 *
b11011 )
#280000
0$
#285000
b1000 #
b1000 +
1$
#286000
b11101 (
b11100 *
b11100 )
#290000
0$
#295000
b1001 #
b1001 +
1$
#296000
b11110 (
b11101 *
b11101 )
#300000
0$
#305000
b11 !
b11 ,
b0 #
b0 +
1$
#306000
b11111 (
b11110 *
b11110 )
#310000
0$
#315000
b1 #
b1 +
1$
#316000
b100000 (
b11111 *
b11111 )
#320000
0$
#325000
b10 #
b10 +
1$
#326000
b100001 (
b100000 *
b100000 )
#330000
0$
#335000
b11 #
b11 +
1$
#336000
b100010 (
b100001 *
b100001 )
#340000
0$
#345000
b100 #
b100 +
1$
#346000
b100011 (
b100010 *
b100010 )
#350000
0$
#355000
b101 #
b101 +
1$
#356000
b100100 (
b100011 *
b100011 )
#360000
0$
#365000
b110 #
b110 +
1$
#366000
b100101 (
b100100 *
b100100 )
#370000
0$
#375000
b111 #
b111 +
1$
#376000
b100110 (
b100101 *
b100101 )
#380000
0$
#385000
b1000 #
b1000 +
1$
#386000
b100111 (
b100110 *
b100110 )
#390000
0$
#395000
b1001 #
b1001 +
1$
#396000
b101000 (
b100111 *
b100111 )
#400000
0$
#405000
b100 !
b100 ,
b0 #
b0 +
1$
#406000
b101001 (
b101000 *
b101000 )
#410000
0$
#415000
b1 #
b1 +
1$
#416000
b101010 (
b101001 *
b101001 )
#420000
0$
#425000
b10 #
b10 +
1$
#426000
b101011 (
b101010 *
b101010 )
#430000
0$
#435000
b11 #
b11 +
1$
#436000
b101100 (
b101011 *
b101011 )
#440000
0$
#445000
b100 #
b100 +
1$
#446000
b101101 (
b101100 *
b101100 )
#450000
0$
#455000
b101 #
b101 +
1$
#456000
b101110 (
b101101 *
b101101 )
#460000
0$
#465000
b110 #
b110 +
1$
#466000
b101111 (
b101110 *
b101110 )
#470000
0$
#475000
b111 #
b111 +
1$
#476000
b110000 (
b101111 *
b101111 )
#480000
0$
#485000
b1000 #
b1000 +
1$
#486000
b110001 (
b110000 *
b110000 )
#490000
0$
#495000
b1001 #
b1001 +
1$
#496000
b110010 (
b110001 *
b110001 )
#500000
0$
#505000
b101 !
b101 ,
b0 #
b0 +
1$
#506000
b110011 (
b110010 *
b110010 )
#510000
0$
#515000
b1 #
b1 +
1$
#516000
b110100 (
b110011 *
b110011 )
#520000
0$
#525000
b10 #
b10 +
1$
#526000
b110101 (
b110100 *
b110100 )
#530000
0$
#535000
b11 #
b11 +
1$
#536000
b110110 (
b110101 *
b110101 )
#540000
0$
#545000
b100 #
b100 +
1$
#546000
b110111 (
b110110 *
b110110 )
#550000
0$
#555000
b101 #
b101 +
1$
#556000
b111000 (
b110111 *
b110111 )
#560000
0$
#565000
b110 #
b110 +
1$
#566000
b111001 (
b111000 *
b111000 )
#570000
0$
#575000
b111 #
b111 +
1$
#576000
b111010 (
b111001 *
b111001 )
#580000
0$
#585000
b1000 #
b1000 +
1$
#586000
b111011 (
b111010 *
b111010 )
#590000
0$
#595000
b1001 #
b1001 +
1$
#596000
b111100 (
b111011 *
b111011 )
#600000
0$
#605000
1"
b110 !
b110 ,
b0 #
b0 +
1$
#606000
b111101 (
b111100 *
b111100 )
#610000
0$
#615000
0"
b0 !
b0 ,
1$
#616000
b111110 (
b0 *
b0 )
#620000
0$
#625000
b1 #
b1 +
1$
#626000
b111111 (
b1 *
b1 )
#630000
0$
#635000
b10 #
b10 +
1$
#636000
b1000000 (
b10 *
b10 )
#640000
0$
#645000
b11 #
b11 +
1$
#646000
b1000001 (
b11 *
b11 )
#650000
0$
#655000
b100 #
b100 +
1$
#656000
b1000010 (
b100 *
b100 )
#660000
0$
#665000
b101 #
b101 +
1$
#666000
b1000011 (
b101 *
b101 )
#670000
0$
#675000
b110 #
b110 +
1$
#676000
b1000100 (
b110 *
b110 )
#680000
0$
#685000
b111 #
b111 +
1$
#686000
b1000101 (
b111 *
b111 )
#690000
0$
#695000
b1000 #
b1000 +
1$
#696000
b1000110 (
b1000 *
b1000 )
#700000
0$
#705000
b1001 #
b1001 +
1$
#706000
b1000111 (
b1001 *
b1001 )
#710000
0$
#715000
b1 !
b1 ,
b0 #
b0 +
1$
#716000
b1001000 (
b1010 *
b1010 )
#720000
0$
#725000
b1 #
b1 +
1$
#726000
b1001001 (
b1011 *
b1011 )
#730000
0$
#735000
b10 #
b10 +
1$
#736000
b1001010 (
b1100 *
b1100 )
#740000
0$
#745000
b11 #
b11 +
1$
#746000
b1001011 (
b1101 *
b1101 )
#750000
0$
#755000
b100 #
b100 +
1$
#756000
b1001100 (
b1110 *
b1110 )
#760000
0$
#765000
b101 #
b101 +
1$
#766000
b1001101 (
b1111 *
b1111 )
#770000
0$
#775000
b110 #
b110 +
1$
#776000
b1001110 (
b10000 *
b10000 )
#780000
0$
#785000
b111 #
b111 +
1$
#786000
b1001111 (
b10001 *
b10001 )
#790000
0$
#795000
b1000 #
b1000 +
1$
#796000
b1010000 (
b10010 *
b10010 )
#800000
0$
#805000
b1001 #
b1001 +
1$
#806000
b1010001 (
b10011 *
b10011 )
#810000
0$
#815000
b10 !
b10 ,
b0 #
b0 +
1$
#816000
b1010010 (
b10100 *
b10100 )
#820000
0$
#825000
b1 #
b1 +
1$
#826000
b1010011 (
b10101 *
b10101 )
#830000
0$
#835000
b10 #
b10 +
1$
#836000
b1010100 (
b10110 *
b10110 )
#840000
0$
#845000
b11 #
b11 +
1$
#846000
b1010101 (
b10111 *
b10111 )
#850000
0$
#855000
b100 #
b100 +
1$
#856000
b1010110 (
b11000 *
b11000 )
#860000
0$
#865000
b101 #
b101 +
1$
#866000
b1010111 (
b11001 *
b11001 )
#870000
0$
#875000
b110 #
b110 +
1$
#876000
b1011000 (
b11010 *
b11010 )
#880000
0$
#885000
b111 #
b111 +
1$
#886000
b1011001 (
b11011 *
b11011 )
#890000
0$
#895000
b1000 #
b1000 +
1$
#896000
b1011010 (
b11100 *
b11100 )
#900000
0$
#905000
b1001 #
b1001 +
1$
#906000
b1011011 (
b11101 *
b11101 )
#910000
0$
#915000
b11 !
b11 ,
b0 #
b0 +
1$
#916000
b1011100 (
b11110 *
b11110 )
#920000
0$
#925000
b1 #
b1 +
1$
#926000
b1011101 (
b11111 *
b11111 )
#930000
0$
#935000
b10 #
b10 +
1$
#936000
b1011110 (
b100000 *
b100000 )
#940000
0$
#945000
b11 #
b11 +
1$
#946000
b1011111 (
b100001 *
b100001 )
#950000
0$
#955000
b100 #
b100 +
1$
#956000
b1100000 (
b100010 *
b100010 )
#960000
0$
#965000
b101 #
b101 +
1$
#966000
b1100001 (
b100011 *
b100011 )
#970000
0$
#975000
b110 #
b110 +
1$
#976000
b1100010 (
b100100 *
b100100 )
#980000
0$
#985000
b111 #
b111 +
1$
#986000
b1100011 (
b100101 *
b100101 )
#990000
0$
#995000
b1000 #
b1000 +
1$
#996000
b1100100 (
b100110 *
b100110 )
#1000000
0$
#1005000
b1001 #
b1001 +
1$
#1006000
b1100101 (
b100111 *
b100111 )
#1010000
0$
#1015000
b100 !
b100 ,
b0 #
b0 +
1$
#1016000
b1100110 (
b101000 *
b101000 )
#1020000
0$
#1025000
b1 #
b1 +
1$
#1026000
b1100111 (
b101001 *
b101001 )
#1030000
0$
#1035000
b10 #
b10 +
1$
#1036000
b1101000 (
b101010 *
b101010 )
#1040000
0$
#1045000
b11 #
b11 +
1$
#1046000
b1101001 (
b101011 *
b101011 )
#1050000
0$
#1055000
b100 #
b100 +
1$
#1056000
b1101010 (
b101100 *
b101100 )
#1060000
0$
#1065000
b101 #
b101 +
1$
#1066000
b1101011 (
b101101 *
b101101 )
#1070000
0$
#1075000
b110 #
b110 +
1$
#1076000
b1101100 (
b101110 *
b101110 )
#1080000
0$
#1085000
b111 #
b111 +
1$
#1086000
b1101101 (
b101111 *
b101111 )
#1090000
0$
#1095000
b1000 #
b1000 +
1$
#1096000
b1101110 (
b110000 *
b110000 )
#1100000
0$
#1105000
b1001 #
b1001 +
1$
#1106000
b1101111 (
b110001 *
b110001 )
#1110000
0$
#1115000
b101 !
b101 ,
b0 #
b0 +
1$
#1116000
b1110000 (
b110010 *
b110010 )
#1120000
0$
#1125000
b1 #
b1 +
1$
#1126000
b1110001 (
b110011 *
b110011 )
#1130000
0$
#1135000
b10 #
b10 +
1$
#1136000
b1110010 (
b110100 *
b110100 )
#1140000
0$
#1145000
b11 #
b11 +
1$
#1146000
b1110011 (
b110101 *
b110101 )
#1150000
0$
#1155000
b100 #
b100 +
1$
#1156000
b1110100 (
b110110 *
b110110 )
#1160000
0$
#1165000
b101 #
b101 +
1$
#1166000
b1110101 (
b110111 *
b110111 )
#1170000
0$
#1175000
b110 #
b110 +
1$
#1176000
b1110110 (
b111000 *
b111000 )
#1180000
0$
#1185000
b111 #
b111 +
1$
#1186000
b1110111 (
b111001 *
b111001 )
#1190000
0$
#1195000
b1000 #
b1000 +
1$
#1196000
b1111000 (
b111010 *
b111010 )
#1200000
0$
#1205000
b1001 #
b1001 +
1$
#1206000
b1111001 (
b111011 *
b111011 )
#1210000
0$
#1215000
1"
b110 !
b110 ,
b0 #
b0 +
1$
#1216000
b1111010 (
b111100 *
b111100 )
#1220000
0$
#1225000
0"
b0 !
b0 ,
1$
#1226000
b1001 -
b1111011 (
b0 *
b0 )
#1230000
0$
#1235000
b1 #
b1 +
1$
#1240000
0$
#1245000
b10 #
b10 +
1$
#1250000
0$
#1255000
b11 #
b11 +
1$
#1260000
0$
#1265000
b100 #
b100 +
1$
#1270000
0$
#1275000
b101 #
b101 +
1$
#1280000
0$
#1285000
b110 #
b110 +
1$
#1290000
0$
#1295000
b111 #
b111 +
1$
#1300000
0$
#1305000
b1000 #
b1000 +
1$
#1310000
0$
#1315000
b1001 #
b1001 +
1$
#1320000
0$
#1325000
b1 !
b1 ,
b0 #
b0 +
1$
#1326000
b111011 -
#1330000
0$
#1335000
b1 #
b1 +
1$
#1340000
0$
#1345000
b10 #
b10 +
1$
#1350000
0$
#1355000
b11 #
b11 +
1$
#1360000
0$
#1365000
b100 #
b100 +
1$
#1370000
0$
#1375000
b101 #
b101 +
1$
#1380000
0$
#1385000
b110 #
b110 +
1$
#1390000
0$
#1395000
b111 #
b111 +
1$
#1400000
0$
#1405000
b1000 #
b1000 +
1$
#1410000
0$
#1415000
b1001 #
b1001 +
1$
#1420000
0$
#1425000
b10 !
b10 ,
b0 #
b0 +
1$
#1430000
0$
#1435000
b1 #
b1 +
1$
#1440000
0$
#1445000
b10 #
b10 +
1$
#1450000
0$
#1455000
b11 #
b11 +
1$
#1460000
0$
#1465000
b100 #
b100 +
1$
#1470000
0$
#1475000
b101 #
b101 +
1$
#1480000
0$
#1485000
b110 #
b110 +
1$
#1490000
0$
#1495000
b111 #
b111 +
1$
#1500000
0$
#1505000
b1000 #
b1000 +
1$
#1510000
0$
#1515000
b1001 #
b1001 +
1$
#1520000
0$
#1525000
b11 !
b11 ,
b0 #
b0 +
1$
#1530000
0$
#1535000
b1 #
b1 +
1$
#1540000
0$
#1545000
b10 #
b10 +
1$
#1550000
0$
#1555000
b11 #
b11 +
1$
#1560000
0$
#1565000
b100 #
b100 +
1$
#1570000
0$
#1575000
b101 #
b101 +
1$
#1580000
0$
#1585000
b110 #
b110 +
1$
#1590000
0$
#1595000
b111 #
b111 +
1$
#1600000
0$
#1605000
b1000 #
b1000 +
1$
#1610000
0$
#1615000
b1001 #
b1001 +
1$
#1620000
0$
#1625000
b100 !
b100 ,
b0 #
b0 +
1$
#1630000
0$
#1635000
b1 #
b1 +
1$
#1640000
0$
#1645000
b10 #
b10 +
1$
#1650000
0$
#1655000
b11 #
b11 +
1$
#1660000
0$
#1665000
b100 #
b100 +
1$
#1670000
0$
#1675000
b101 #
b101 +
1$
#1680000
0$
#1685000
b110 #
b110 +
1$
#1690000
0$
#1695000
b111 #
b111 +
1$
#1700000
0$
#1705000
b1000 #
b1000 +
1$
#1710000
0$
#1715000
b1001 #
b1001 +
1$
#1720000
0$
#1725000
b101 !
b101 ,
b0 #
b0 +
1$
#1730000
0$
#1735000
b1 #
b1 +
1$
#1740000
0$
#1745000
b10 #
b10 +
1$
#1750000
0$
#1755000
b11 #
b11 +
1$
#1760000
0$
#1765000
b100 #
b100 +
1$
#1770000
0$
#1775000
b101 #
b101 +
1$
#1780000
0$
#1785000
b110 #
b110 +
1$
#1790000
0$
#1795000
b111 #
b111 +
1$
#1800000
0$
#1805000
b1000 #
b1000 +
1$
#1810000
0$
#1815000
b1001 #
b1001 +
1$
#1820000
0$
#1825000
1"
b110 !
b110 ,
b0 #
b0 +
1$
#1830000
0$
#1835000
0"
b0 !
b0 ,
1$
#1836000
b101 -
#1840000
0$
#1845000
b1 #
b1 +
1$
#1850000
0$
#1855000
b10 #
b10 +
1$
#1860000
0$
#1865000
b11 #
b11 +
1$
#1870000
0$
#1875000
b100 #
b100 +
1$
#1880000
0$
#1885000
b101 #
b101 +
1$
#1886000
b0 (
0%
#1890000
0$
#1895000
1$
#1896000
b1 (
#1900000
0$
#1905000
1$
#1906000
b10 (
#1910000
0$
#1915000
1$
#1916000
b11 (
#1920000
0$
#1925000
1$
#1926000
1%
b100 (
#1930000
0$
#1935000
b110 #
b110 +
1$
#1936000
b111100 -
#1940000
0$
#1945000
b111 #
b111 +
1$
#1950000
0$
#1955000
b1000 #
b1000 +
1$
#1960000
0$
#1965000
b1001 #
b1001 +
1$
#1970000
0$
#1975000
b1 !
b1 ,
b0 #
b0 +
1$
#1980000
0$
#1985000
b1 #
b1 +
1$
#1990000
0$
#1995000
b10 #
b10 +
1$
#2000000
0$
#2005000
b11 #
b11 +
1$
#2010000
0$
#2015000
b100 #
b100 +
1$
#2020000
0$
#2025000
b101 #
b101 +
1$
#2030000
0$
#2035000
b110 #
b110 +
1$
#2040000
0$
#2045000
b111 #
b111 +
1$
#2050000
0$
#2055000
b1000 #
b1000 +
1$
#2060000
0$
#2065000
b1001 #
b1001 +
1$
#2070000
0$
#2075000
b10 !
b10 ,
b0 #
b0 +
1$
#2080000
0$
#2085000
b1 #
b1 +
1$
#2090000
0$
#2095000
b10 #
b10 +
1$
#2100000
0$
#2105000
b11 #
b11 +
1$
#2110000
0$
#2115000
b100 #
b100 +
1$
#2120000
0$
#2125000
b101 #
b101 +
1$
#2130000
0$
#2135000
b110 #
b110 +
1$
#2140000
0$
#2145000
b111 #
b111 +
1$
#2150000
0$
#2155000
b1000 #
b1000 +
1$
#2160000
0$
#2165000
b1001 #
b1001 +
1$
#2170000
0$
#2175000
b11 !
b11 ,
b0 #
b0 +
1$
#2180000
0$
#2185000
b1 #
b1 +
1$
#2190000
0$
#2195000
b10 #
b10 +
1$
#2200000
0$
#2205000
b11 #
b11 +
1$
#2210000
0$
#2215000
b100 #
b100 +
1$
#2220000
0$
#2225000
b101 #
b101 +
1$
#2230000
0$
#2235000
b110 #
b110 +
1$
#2240000
0$
#2245000
b111 #
b111 +
1$
#2250000
0$
#2255000
b1000 #
b1000 +
1$
#2260000
0$
#2265000
b1001 #
b1001 +
1$
#2270000
0$
#2275000
b100 !
b100 ,
b0 #
b0 +
1$
#2280000
0$
#2285000
b1 #
b1 +
1$
#2290000
0$
#2295000
b10 #
b10 +
1$
#2300000
0$
#2305000
b11 #
b11 +
1$
#2310000
0$
#2315000
b100 #
b100 +
1$
#2320000
0$
#2325000
b101 #
b101 +
1$
#2330000
0$
#2335000
b110 #
b110 +
1$
#2340000
0$
#2345000
b111 #
b111 +
1$
#2350000
0$
#2355000
b1000 #
b1000 +
1$
#2360000
0$
#2365000
b1001 #
b1001 +
1$
#2370000
0$
#2375000
b101 !
b101 ,
b0 #
b0 +
1$
#2380000
0$
#2385000
b1 #
b1 +
1$
#2390000
0$
#2395000
b10 #
b10 +
1$
#2400000
0$
#2405000
b11 #
b11 +
1$
#2410000
0$
#2415000
b100 #
b100 +
1$
#2420000
0$
#2425000
b101 #
b101 +
1$
#2430000
0$
#2435000
b110 #
b110 +
1$
#2440000
0$
#2445000
b111 #
b111 +
1$
#2450000
0$
#2455000
b1000 #
b1000 +
1$
#2460000
0$
#2465000
b1001 #
b1001 +
1$
#2470000
0$
#2475000
1"
b110 !
b110 ,
b0 #
b0 +
1$
#2480000
0$
#2485000
0"
b0 !
b0 ,
1$
